{
  "id": "dd744ca738ffb7562b52a026b99db09d",
  "layout": {
    "bounds": [
      1.5055,
      1.5046,
      264.45,
      281.24
    ],
    "vars": {
      "c_1": {
        "x": 126.67,
        "y": 149.12
      },
      "c_10": {
        "x": 121.0,
        "y": 116.32
      },
      "c_100": {
        "x": 195.6,
        "y": 237.19
      },
      "c_11": {
        "x": 100.46,
        "y": 101.55
      },
      "c_12": {
        "x": 94.176,
        "y": 105.39
      },
      "c_13": {
        "x": 95.051,
        "y": 102.2
      },
      "c_14": {
        "x": 90.192,
        "y": 84.228
      },
      "c_15": {
        "x": 71.041,
        "y": 93.224
      },
      "c_16": {
        "x": 50.5,
        "y": 84.109
      },
      "c_17": {
        "x": 144.46,
        "y": 91.33
      },
      "c_18": {
        "x": 161.34,
        "y": 67.735
      },
      "c_19": {
        "x": 167.24,
        "y": 72.08
      },
      "c_2": {
        "x": 121.99,
        "y": 152.88
      },
      "c_20": {
        "x": 166.18,
        "y": 68.736
      },
      "c_21": {
        "x": 170.35,
        "y": 50.273
      },
      "c_22": {
        "x": 189.48,
        "y": 56.529
      },
      "c_23": {
        "x": 213.17,
        "y": 41.224
      },
      "c_24": {
        "x": 235.78,
        "y": 26.748
      },
      "c_25": {
        "x": 256.02,
        "y": 19.514
      },
      "c_26": {
        "x": 116.09,
        "y": 126.99
      },
      "c_27": {
        "x": 111.56,
        "y": 100.42
      },
      "c_28": {
        "x": 106.52,
        "y": 75.733
      },
      "c_29": {
        "x": 100.84,
        "y": 54.754
      },
      "c_3": {
        "x": 119.04,
        "y": 177.77
      },
      "c_30": {
        "x": 121.4,
        "y": 202.3
      },
      "c_31": {
        "x": 142.0,
        "y": 222.7
      },
      "c_32": {
        "x": 169.09,
        "y": 235.11
      },
      "c_33": {
        "x": 165.22,
        "y": 189.23
      },
      "c_34": {
        "x": 156.15,
        "y": 195.89
      },
      "c_35": {
        "x": 162.48,
        "y": 194.68
      },
      "c_36": {
        "x": 166.16,
        "y": 217.16
      },
      "c_37": {
        "x": 178.28,
        "y": 235.95
      },
      "c_38": {
        "x": 91.464,
        "y": 202.93
      },
      "c_39": {
        "x": 84.932,
        "y": 201.6
      },
      "c_4": {
        "x": 139.05,
        "y": 175.82
      },
      "c_40": {
        "x": 79.081,
        "y": 195.57
      },
      "c_41": {
        "x": 88.22,
        "y": 204.16
      },
      "c_42": {
        "x": 80.545,
        "y": 221.14
      },
      "c_43": {
        "x": 68.223,
        "y": 221.62
      },
      "c_44": {
        "x": 50.991,
        "y": 241.4
      },
      "c_45": {
        "x": 35.78,
        "y": 259.45
      },
      "c_46": {
        "x": 23.029,
        "y": 274.93
      },
      "c_47": {
        "x": 52.616,
        "y": 201.66
      },
      "c_48": {
        "x": 29.468,
        "y": 207.79
      },
      "c_49": {
        "x": 9.6484,
        "y": 213.3
      },
      "c_5": {
        "x": 109.4,
        "y": 179.06
      },
      "c_50": {
        "x": 175.82,
        "y": 178.38
      },
      "c_51": {
        "x": 161.34,
        "y": 182.68
      },
      "c_52": {
        "x": 173.18,
        "y": 182.86
      },
      "c_53": {
        "x": 203.88,
        "y": 183.92
      },
      "c_54": {
        "x": 200.99,
        "y": 188.9
      },
      "c_55": {
        "x": 204.39,
        "y": 187.32
      },
      "c_56": {
        "x": 213.98,
        "y": 204.47
      },
      "c_57": {
        "x": 220.89,
        "y": 206.45
      },
      "c_58": {
        "x": 216.79,
        "y": 223.26
      },
      "c_59": {
        "x": 165.94,
        "y": 199.38
      },
      "c_6": {
        "x": 143.31,
        "y": 170.31
      },
      "c_60": {
        "x": 155.81,
        "y": 199.89
      },
      "c_61": {
        "x": 160.36,
        "y": 202.17
      },
      "c_62": {
        "x": 178.22,
        "y": 212.11
      },
      "c_63": {
        "x": 147.58,
        "y": 218.18
      },
      "c_64": {
        "x": 216.72,
        "y": 229.85
      },
      "c_65": {
        "x": 219.3,
        "y": 226.63
      },
      "c_66": {
        "x": 230.86,
        "y": 241.5
      },
      "c_67": {
        "x": 74.588,
        "y": 91.063
      },
      "c_68": {
        "x": 77.876,
        "y": 88.007
      },
      "c_69": {
        "x": 63.912,
        "y": 76.875
      },
      "c_7": {
        "x": 123.5,
        "y": 148.35
      },
      "c_70": {
        "x": 228.32,
        "y": 185.05
      },
      "c_71": {
        "x": 228.84,
        "y": 188.38
      },
      "c_72": {
        "x": 246.78,
        "y": 184.09
      },
      "c_73": {
        "x": 183.55,
        "y": 199.81
      },
      "c_74": {
        "x": 184.14,
        "y": 195.66
      },
      "c_75": {
        "x": 199.14,
        "y": 201.65
      },
      "c_76": {
        "x": 187.18,
        "y": 249.13
      },
      "c_77": {
        "x": 184.02,
        "y": 249.56
      },
      "c_78": {
        "x": 188.35,
        "y": 267.48
      },
      "c_79": {
        "x": 102.51,
        "y": 190.35
      },
      "c_8": {
        "x": 114.59,
        "y": 121.4
      },
      "c_80": {
        "x": 102.98,
        "y": 187.07
      },
      "c_81": {
        "x": 85.614,
        "y": 184.71
      },
      "c_82": {
        "x": 254.76,
        "y": 14.519
      },
      "c_83": {
        "x": 251.65,
        "y": 11.149
      },
      "c_84": {
        "x": 264.45,
        "y": 1.5046
      },
      "c_85": {
        "x": 239.21,
        "y": 223.13
      },
      "c_86": {
        "x": 240.26,
        "y": 219.92
      },
      "c_87": {
        "x": 256.7,
        "y": 228.11
      },
      "c_88": {
        "x": 155.68,
        "y": 66.178
      },
      "c_89": {
        "x": 152.21,
        "y": 66.714
      },
      "c_9": {
        "x": 128.36,
        "y": 119.08
      },
      "c_90": {
        "x": 151.96,
        "y": 49.752
      },
      "c_91": {
        "x": 223.31,
        "y": 178.14
      },
      "c_92": {
        "x": 226.51,
        "y": 181.33
      },
      "c_93": {
        "x": 239.42,
        "y": 168.81
      },
      "c_94": {
        "x": 116.81,
        "y": 160.55
      },
      "c_95": {
        "x": 115.54,
        "y": 164.13
      },
      "c_96": {
        "x": 100.79,
        "y": 156.85
      },
      "c_97": {
        "x": 181.24,
        "y": 205.38
      },
      "c_98": {
        "x": 197.24,
        "y": 229.66
      },
      "c_99": {
        "x": 198.84,
        "y": 217.81
      },
      "var_1": {
        "x": 125.32,
        "y": 165.47
      },
      "var_10": {
        "x": 94.356,
        "y": 93.659
      },
      "var_11": {
        "x": 83.368,
        "y": 97.1
      },
      "var_12": {
        "x": 86.632,
        "y": 76.226
      },
      "var_13": {
        "x": 60.036,
        "y": 88.769
      },
      "var_14": {
        "x": 42.623,
        "y": 79.911
      },
      "var_15": {
        "x": 155.79,
        "y": 76.554
      },
      "var_16": {
        "x": 166.93,
        "y": 59.795
      },
      "var_17": {
        "x": 177.05,
        "y": 64.464
      },
      "var_18": {
        "x": 172.96,
        "y": 42.14
      },
      "var_19": {
        "x": 201.48,
        "y": 48.745
      },
      "var_2": {
        "x": 123.18,
        "y": 132.25
      },
      "var_20": {
        "x": 224.59,
        "y": 33.864
      },
      "var_21": {
        "x": 246.75,
        "y": 19.811
      },
      "var_22": {
        "x": 264.18,
        "y": 18.244
      },
      "var_23": {
        "x": 113.68,
        "y": 113.65
      },
      "var_24": {
        "x": 109.15,
        "y": 87.698
      },
      "var_25": {
        "x": 103.67,
        "y": 64.663
      },
      "var_26": {
        "x": 98.341,
        "y": 46.41
      },
      "var_27": {
        "x": 130.83,
        "y": 213.2
      },
      "var_28": {
        "x": 154.89,
        "y": 230.18
      },
      "var_29": {
        "x": 183.99,
        "y": 237.23
      },
      "var_3": {
        "x": 119.28,
        "y": 140.26
      },
      "var_30": {
        "x": 174.21,
        "y": 196.56
      },
      "var_31": {
        "x": 161.97,
        "y": 205.34
      },
      "var_32": {
        "x": 171.53,
        "y": 227.54
      },
      "var_33": {
        "x": 187.18,
        "y": 240.5
      },
      "var_34": {
        "x": 85.594,
        "y": 211.98
      },
      "var_35": {
        "x": 78.203,
        "y": 211.12
      },
      "var_36": {
        "x": 65.373,
        "y": 198.59
      },
      "var_37": {
        "x": 76.285,
        "y": 228.87
      },
      "var_38": {
        "x": 59.271,
        "y": 231.72
      },
      "var_39": {
        "x": 43.096,
        "y": 250.69
      },
      "var_4": {
        "x": 113.43,
        "y": 190.16
      },
      "var_40": {
        "x": 29.09,
        "y": 267.58
      },
      "var_41": {
        "x": 17.822,
        "y": 281.24
      },
      "var_42": {
        "x": 40.546,
        "y": 204.77
      },
      "var_43": {
        "x": 19.095,
        "y": 210.65
      },
      "var_44": {
        "x": 1.5055,
        "y": 215.57
      },
      "var_45": {
        "x": 189.91,
        "y": 183.4
      },
      "var_46": {
        "x": 161.97,
        "y": 191.38
      },
      "var_47": {
        "x": 217.09,
        "y": 188.36
      },
      "var_48": {
        "x": 211.15,
        "y": 195.83
      },
      "var_49": {
        "x": 209.27,
        "y": 220.38
      },
      "var_5": {
        "x": 152.71,
        "y": 185.94
      },
      "var_50": {
        "x": 228.7,
        "y": 217.72
      },
      "var_51": {
        "x": 207.21,
        "y": 231.78
      },
      "var_52": {
        "x": 169.06,
        "y": 207.07
      },
      "var_53": {
        "x": 152.87,
        "y": 208.93
      },
      "var_54": {
        "x": 188.09,
        "y": 213.35
      },
      "var_55": {
        "x": 143.71,
        "y": 226.63
      },
      "var_56": {
        "x": 226.87,
        "y": 234.15
      },
      "var_57": {
        "x": 223.8,
        "y": 237.63
      },
      "var_58": {
        "x": 70.867,
        "y": 80.669
      },
      "var_59": {
        "x": 67.353,
        "y": 84.028
      },
      "var_6": {
        "x": 93.695,
        "y": 192.63
      },
      "var_60": {
        "x": 239.25,
        "y": 187.39
      },
      "var_61": {
        "x": 238.69,
        "y": 183.36
      },
      "var_62": {
        "x": 192.95,
        "y": 197.16
      },
      "var_63": {
        "x": 191.96,
        "y": 202.51
      },
      "var_64": {
        "x": 185.07,
        "y": 260.01
      },
      "var_65": {
        "x": 189.2,
        "y": 259.44
      },
      "var_66": {
        "x": 93.458,
        "y": 184.36
      },
      "var_67": {
        "x": 92.771,
        "y": 188.36
      },
      "var_68": {
        "x": 257.53,
        "y": 4.321
      },
      "var_69": {
        "x": 261.45,
        "y": 8.3317
      },
      "var_7": {
        "x": 160.91,
        "y": 175.67
      },
      "var_70": {
        "x": 250.17,
        "y": 223.24
      },
      "var_71": {
        "x": 248.72,
        "y": 227.34
      },
      "var_72": {
        "x": 150.46,
        "y": 57.302
      },
      "var_73": {
        "x": 155.02,
        "y": 56.74
      },
      "var_74": {
        "x": 234.73,
        "y": 175.2
      },
      "var_75": {
        "x": 231.53,
        "y": 171.68
      },
      "var_76": {
        "x": 106.76,
        "y": 161.53
      },
      "var_77": {
        "x": 108.36,
        "y": 156.99
      },
      "var_8": {
        "x": 106.36,
        "y": 110.43
      },
      "var_9": {
        "x": 133.07,
        "y": 106.18
      }
    }
  }
}
