<layout>
  <level id="LockedWidget" qid="3" tutorial="locked">
    <box height="1.0" id="LockedWidget1" lines="1" width="1.81" x="3.83" y="3.90" visible="true"/>
    <box height="1.0" id="LockedWidget2" lines="1" width="1.81" x="5.50" y="1.39" visible="true"/>
    <box height="1.0" id="LockedWidget3" lines="3" width="3.0" x="10.86" y="3.85" visible="true"/>
    <box height="1.0" id="LockedWidget4" lines="2" width="2.4" x="7.17" y="4.85" visible="true"/>
    <box height="1.0" id="LockedWidget5" lines="1" width="1.81" x="9.09" y="1.39" visible="true"/>
    <joint height="0.51" id="n10__IN__0" inputs="1" kind="OUTGOING" outputs="0" width="0.59" x="0.88" y="5.82" visible="false"/>
    <joint height="0.51" id="n20" inputs="1" kind="END" outputs="0" width="0.59" x="3.68" y="5.82" visible="false"/>
    <joint height="0.51" id="n310" inputs="1" kind="END" outputs="0" width="0.59" x="5.49" y="5.82" visible="false"/>
    <joint height="0.51" id="n420" inputs="1" kind="END" outputs="0" width="0.59" x="12.4" y="5.82" visible="false"/>
    <joint height="0.51" id="n50" inputs="1" kind="END" outputs="0" width="0.59" x="14.33" y="5.82" visible="false"/>
    <joint height="0.51" id="n5" inputs="0" kind="START_PIPE_DEPENDENT_BALL" outputs="1" width="0.59" x="14.33" y="0.26" visible="false"/>
    <joint height="0.51" id="n42__OUT__0" inputs="0" kind="INCOMING" outputs="1" width="0.59" x="11.97" y="0.26" visible="false"/>
    <joint height="0.51" id="n41__OUT__0" inputs="0" kind="INCOMING" outputs="1" width="0.59" x="10.38" y="0.26" visible="false"/>
    <joint height="0.51" id="n410" inputs="1" kind="END" outputs="0" width="0.59" x="10.81" y="5.82" visible="false"/>
    <joint height="0.51" id="n31" inputs="0" kind="START_PIPE_DEPENDENT_BALL" outputs="1" width="0.59" x="5.49" y="0.26" visible="false"/>
    <joint height="0.51" id="n1" inputs="0" kind="START_PIPE_DEPENDENT_BALL" outputs="1" width="0.59" x="0.88" y="0.26" visible="false"/>
    <joint height="0.51" id="n2" inputs="0" kind="START_PIPE_DEPENDENT_BALL" outputs="1" width="0.59" x="3.68" y="0.26" visible="false"/>
    <joint height="0.51" id="n33" inputs="0" kind="START_PIPE_DEPENDENT_BALL" outputs="1" width="0.59" x="8.68" y="0.26" visible="false"/>
    <joint height="0.51" id="n330" inputs="1" kind="END" outputs="0" width="0.59" x="8.68" y="5.82" visible="false"/>
    <joint height="0.51" id="n32__OUT__0" inputs="0" kind="INCOMING" outputs="1" width="0.59" x="7.08" y="0.26" visible="false"/>
    <joint height="0.51" id="n320" inputs="1" kind="END" outputs="0" width="0.59" x="7.08" y="5.82" visible="false"/>
    <line id="e1__IN__">
      <fromjoint id="n1" port="0"/>
      <tobox id="LockedWidget1" port="0"/>
      <point x="0.89" y="0.53"/>
      <point x="0.89" y="0.91"/>
      <point x="0.89" y="2.15"/>
      <point x="0.89" y="2.53"/>
    </line>
    <line id="e1__OUT__">
      <frombox id="LockedWidget1" port="0"/>
      <tojoint id="n10__IN__0" port="0"/>
      <point x="0.89" y="3.56"/>
      <point x="0.89" y="3.94"/>
      <point x="0.89" y="5.18"/>
      <point x="0.89" y="5.56"/>
    </line>
    <line id="e2__IN__">
      <fromjoint id="n2" port="0"/>
      <tobox id="LockedWidget2" port="0"/>
      <point x="3.69" y="0.53"/>
      <point x="3.69" y="0.91"/>
      <point x="3.69" y="2.15"/>
      <point x="3.69" y="2.53"/>
    </line>
    <line id="e2__OUT__">
      <frombox id="LockedWidget2" port="0"/>
      <tojoint id="n20" port="0"/>
      <point x="3.69" y="3.56"/>
      <point x="3.69" y="3.94"/>
      <point x="3.69" y="5.18"/>
      <point x="3.69" y="5.56"/>
    </line>
    <line id="e31__IN__">
      <fromjoint id="n31" port="0"/>
      <tobox id="LockedWidget3" port="0"/>
      <point x="5.5" y="0.53"/>
      <point x="5.5" y="0.91"/>
      <point x="6.0" y="0.91"/>
      <point x="6.0" y="2.16"/>
      <point x="6.49" y="2.16"/>
      <point x="6.49" y="2.53"/>
    </line>
    <line id="e31__OUT__">
      <frombox id="LockedWidget3" port="0"/>
      <tojoint id="n310" port="0"/>
      <point x="6.49" y="3.56"/>
      <point x="6.49" y="3.93"/>
      <point x="6.0" y="3.93"/>
      <point x="6.0" y="5.18"/>
      <point x="5.5" y="5.18"/>
      <point x="5.5" y="5.56"/>
    </line>
    <line id="e32__IN__">
      <fromjoint id="n32__OUT__0" port="0"/>
      <tobox id="LockedWidget3" port="1"/>
      <point x="7.1" y="0.53"/>
      <point x="7.1" y="0.91"/>
      <point x="7.1" y="1.78"/>
      <point x="7.1" y="2.53"/>
    </line>
    <line id="e32__OUT__">
      <frombox id="LockedWidget3" port="1"/>
      <tojoint id="n320" port="0"/>
      <point x="7.1" y="3.56"/>
      <point x="7.1" y="4.31"/>
      <point x="7.1" y="5.18"/>
      <point x="7.1" y="5.56"/>
    </line>
    <line id="e33__IN__">
      <fromjoint id="n33" port="0"/>
      <tobox id="LockedWidget3" port="2"/>
      <point x="8.69" y="0.53"/>
      <point x="8.69" y="0.91"/>
      <point x="8.21" y="0.91"/>
      <point x="8.21" y="1.41"/>
      <point x="7.72" y="1.41"/>
      <point x="7.72" y="2.53"/>
    </line>
    <line id="e33__OUT__">
      <frombox id="LockedWidget3" port="2"/>
      <tojoint id="n330" port="0"/>
      <point x="7.72" y="3.56"/>
      <point x="7.72" y="4.68"/>
      <point x="8.21" y="4.68"/>
      <point x="8.21" y="5.18"/>
      <point x="8.69" y="5.18"/>
      <point x="8.69" y="5.56"/>
    </line>
    <line id="e41__IN__">
      <fromjoint id="n41__OUT__0" port="0"/>
      <tobox id="LockedWidget4" port="0"/>
      <point x="10.39" y="0.53"/>
      <point x="10.39" y="0.91"/>
      <point x="10.66" y="0.91"/>
      <point x="10.66" y="2.15"/>
      <point x="10.93" y="2.15"/>
      <point x="10.93" y="2.525"/>
    </line>
    <line id="e41__OUT__">
      <frombox id="LockedWidget4" port="0"/>
      <tojoint id="n410" port="0"/>
      <point x="10.93" y="3.555"/>
      <point x="10.93" y="3.93"/>
      <point x="10.88" y="3.93"/>
      <point x="10.88" y="5.18"/>
      <point x="10.82" y="5.18"/>
      <point x="10.82" y="5.56"/>
    </line>
    <line id="e42__IN__">
      <fromjoint id="n42__OUT__0" port="0"/>
      <tobox id="LockedWidget4" port="1"/>
      <point x="11.99" y="0.53"/>
      <point x="11.99" y="0.91"/>
      <point x="11.78" y="0.91"/>
      <point x="11.78" y="1.77"/>
      <point x="11.56" y="1.77"/>
      <point x="11.56" y="2.525"/>
    </line>
    <line id="e42__OUT__">
      <frombox id="LockedWidget4" port="1"/>
      <tojoint id="n420" port="0"/>
      <point x="11.56" y="3.555"/>
      <point x="11.56" y="4.3"/>
      <point x="11.99" y="4.3"/>
      <point x="11.99" y="5.18"/>
      <point x="12.42" y="5.18"/>
      <point x="12.42" y="5.56"/>
    </line>
    <line id="e5__IN__">
      <fromjoint id="n5" port="0"/>
      <tobox id="LockedWidget5" port="0"/>
      <point x="14.35" y="0.53"/>
      <point x="14.35" y="0.91"/>
      <point x="14.35" y="2.15"/>
      <point x="14.35" y="2.53"/>
    </line>
    <line id="e5__OUT__">
      <frombox id="LockedWidget5" port="0"/>
      <tojoint id="n50" port="0"/>
      <point x="14.35" y="3.56"/>
      <point x="14.35" y="3.94"/>
      <point x="14.35" y="5.18"/>
      <point x="14.35" y="5.56"/>
    </line>
  </level>
</layout>