{
  "id": "4573a5a59cfaff7f285d2b162af442f0",
  "layout": {
    "bounds": [
      15.3333835602,
      16.4999504089,
      269.500061035,
      269.0
    ],
    "vars": {
      "c_1": {
        "x": 207.000045776,
        "y": 197.142944336
      },
      "c_10": {
        "x": 242.000045776,
        "y": 59.0
      },
      "c_100": {
        "x": 78.0000534058,
        "y": 110.0
      },
      "c_101": {
        "x": 102.000053406,
        "y": 29.0
      },
      "c_102": {
        "x": 214.500045776,
        "y": 136.333587646
      },
      "c_103": {
        "x": 157.60005188,
        "y": 134.0
      },
      "c_104": {
        "x": 75.8889389038,
        "y": 123.0
      },
      "c_105": {
        "x": 76.0000534058,
        "y": 46.0
      },
      "c_106": {
        "x": 197.000045776,
        "y": 87.0000534058
      },
      "c_107": {
        "x": 35.5000495911,
        "y": 70.0
      },
      "c_108": {
        "x": 112.000053406,
        "y": 244.499954224
      },
      "c_109": {
        "x": 132.000045776,
        "y": 156.499954224
      },
      "c_11": {
        "x": 237.500045776,
        "y": 136.0
      },
      "c_110": {
        "x": 95.0000534058,
        "y": 165.999954224
      },
      "c_111": {
        "x": 124.000053406,
        "y": 136.999954224
      },
      "c_112": {
        "x": 125.000053406,
        "y": 260.0
      },
      "c_113": {
        "x": 206.000045776,
        "y": 218.999954224
      },
      "c_114": {
        "x": 55.8889389038,
        "y": 120.0
      },
      "c_115": {
        "x": 69.0000534058,
        "y": 259.0
      },
      "c_116": {
        "x": 250.000045776,
        "y": 71.0
      },
      "c_117": {
        "x": 146.000045776,
        "y": 211.249954224
      },
      "c_118": {
        "x": 55.0000495911,
        "y": 90.6666641235
      },
      "c_119": {
        "x": 213.000045776,
        "y": 105.0
      },
      "c_12": {
        "x": 73.3333816528,
        "y": 220.0
      },
      "c_120": {
        "x": 74.0000534058,
        "y": 247.999954224
      },
      "c_121": {
        "x": 85.5000534058,
        "y": 144.0
      },
      "c_122": {
        "x": 222.000045776,
        "y": 113.500053406
      },
      "c_123": {
        "x": 146.750045776,
        "y": 136.0
      },
      "c_124": {
        "x": 102.000053406,
        "y": 253.0
      },
      "c_125": {
        "x": 194.000045776,
        "y": 211.0
      },
      "c_126": {
        "x": 148.000045776,
        "y": 181.999954224
      },
      "c_127": {
        "x": 60.0000495911,
        "y": 211.0
      },
      "c_128": {
        "x": 97.0000534058,
        "y": 232.0
      },
      "c_129": {
        "x": 51.0000495911,
        "y": 139.0
      },
      "c_13": {
        "x": 176.000045776,
        "y": 238.0
      },
      "c_130": {
        "x": 131.000045776,
        "y": 59.0
      },
      "c_131": {
        "x": 158.000045776,
        "y": 117.0
      },
      "c_132": {
        "x": 233.000045776,
        "y": 219.0
      },
      "c_133": {
        "x": 141.750045776,
        "y": 134.0
      },
      "c_134": {
        "x": 237.666717529,
        "y": 189.0
      },
      "c_135": {
        "x": 163.526367188,
        "y": 95.0001144409
      },
      "c_136": {
        "x": 126.000053406,
        "y": 53.9999008179
      },
      "c_137": {
        "x": 112.000053406,
        "y": 226.000045776
      },
      "c_138": {
        "x": 181.000045776,
        "y": 28.0
      },
      "c_139": {
        "x": 238.000045776,
        "y": 74.0
      },
      "c_14": {
        "x": 201.000045776,
        "y": 243.0
      },
      "c_140": {
        "x": 70.0000534058,
        "y": 240.666763306
      },
      "c_141": {
        "x": 132.000045776,
        "y": 203.0
      },
      "c_142": {
        "x": 162.333389282,
        "y": 67.0
      },
      "c_143": {
        "x": 224.000045776,
        "y": 89.0
      },
      "c_144": {
        "x": 175.000045776,
        "y": 194.500198364
      },
      "c_145": {
        "x": 34.0000495911,
        "y": 80.0
      },
      "c_146": {
        "x": 119.200050354,
        "y": 181.0
      },
      "c_147": {
        "x": 191.000045776,
        "y": 148.0
      },
      "c_148": {
        "x": 241.000045776,
        "y": 118.00012207
      },
      "c_149": {
        "x": 45.0000495911,
        "y": 210.0
      },
      "c_15": {
        "x": 135.000045776,
        "y": 175.500045776
      },
      "c_150": {
        "x": 153.500045776,
        "y": 246.599960327
      },
      "c_151": {
        "x": 85.0000534058,
        "y": 209.286010742
      },
      "c_152": {
        "x": 199.60005188,
        "y": 129.166717529
      },
      "c_153": {
        "x": 109.000053406,
        "y": 50.9999008179
      },
      "c_154": {
        "x": 209.000045776,
        "y": 52.9999351501
      },
      "c_155": {
        "x": 219.000045776,
        "y": 237.0
      },
      "c_156": {
        "x": 250.000045776,
        "y": 136.000106812
      },
      "c_157": {
        "x": 107.166717529,
        "y": 198.0
      },
      "c_158": {
        "x": 34.0000495911,
        "y": 123.333236694
      },
      "c_159": {
        "x": 80.3333816528,
        "y": 183.0
      },
      "c_16": {
        "x": 249.250045776,
        "y": 143.0
      },
      "c_160": {
        "x": 162.000045776,
        "y": 174.000045776
      },
      "c_161": {
        "x": 71.4000473022,
        "y": 175.800018311
      },
      "c_162": {
        "x": 158.000045776,
        "y": 218.833435059
      },
      "c_163": {
        "x": 152.000045776,
        "y": 85.8419418335
      },
      "c_164": {
        "x": 181.500045776,
        "y": 214.0
      },
      "c_165": {
        "x": 32.0000495911,
        "y": 128.333328247
      },
      "c_166": {
        "x": 184.000045776,
        "y": 171.500045776
      },
      "c_167": {
        "x": 141.000045776,
        "y": 168.000045776
      },
      "c_168": {
        "x": 210.666717529,
        "y": 111.0
      },
      "c_169": {
        "x": 148.526367188,
        "y": 95.8421401978
      },
      "c_17": {
        "x": 236.000045776,
        "y": 102.999816895
      },
      "c_170": {
        "x": 169.000045776,
        "y": 79.9998092651
      },
      "c_171": {
        "x": 83.5714797974,
        "y": 152.0
      },
      "c_172": {
        "x": 114.909141541,
        "y": 101.333335876
      },
      "c_173": {
        "x": 91.4000473022,
        "y": 173.0
      },
      "c_174": {
        "x": 206.000045776,
        "y": 239.000045776
      },
      "c_175": {
        "x": 244.250045776,
        "y": 145.0
      },
      "c_176": {
        "x": 60.8889389038,
        "y": 121.0
      },
      "c_177": {
        "x": 179.200042725,
        "y": 120.0
      },
      "c_178": {
        "x": 138.000045776,
        "y": 50.0000495911
      },
      "c_179": {
        "x": 126.000053406,
        "y": 32.0
      },
      "c_18": {
        "x": 259.000061035,
        "y": 130.0
      },
      "c_180": {
        "x": 149.000045776,
        "y": 110.842445374
      },
      "c_181": {
        "x": 98.5714797974,
        "y": 148.0
      },
      "c_182": {
        "x": 229.000045776,
        "y": 151.750152588
      },
      "c_183": {
        "x": 184.000045776,
        "y": 269.0
      },
      "c_184": {
        "x": 68.0000534058,
        "y": 235.666671753
      },
      "c_185": {
        "x": 135.000045776,
        "y": 170.499954224
      },
      "c_186": {
        "x": 105.000053406,
        "y": 247.0
      },
      "c_187": {
        "x": 145.466720581,
        "y": 221.250152588
      },
      "c_188": {
        "x": 169.000045776,
        "y": 211.999954224
      },
      "c_189": {
        "x": 257.000061035,
        "y": 170.0
      },
      "c_19": {
        "x": 112.333381653,
        "y": 146.000274658
      },
      "c_190": {
        "x": 211.000045776,
        "y": 121.333282471
      },
      "c_191": {
        "x": 115.000053406,
        "y": 35.9999504089
      },
      "c_192": {
        "x": 153.000045776,
        "y": 184.0
      },
      "c_193": {
        "x": 30.0000495911,
        "y": 202.0
      },
      "c_194": {
        "x": 151.000045776,
        "y": 256.600158691
      },
      "c_195": {
        "x": 198.000045776,
        "y": 236.499954224
      },
      "c_196": {
        "x": 96.0000534058,
        "y": 237.000106812
      },
      "c_197": {
        "x": 129.200042725,
        "y": 180.499954224
      },
      "c_198": {
        "x": 91.0000534058,
        "y": 88.9999465942
      },
      "c_199": {
        "x": 105.333381653,
        "y": 162.0
      },
      "c_2": {
        "x": 34.5000495911,
        "y": 117.000053406
      },
      "c_20": {
        "x": 138.000045776,
        "y": 202.000152588
      },
      "c_200": {
        "x": 75.0000534058,
        "y": 79.0
      },
      "c_201": {
        "x": 47.0000495911,
        "y": 106.0
      },
      "c_202": {
        "x": 91.0000534058,
        "y": 184.285507202
      },
      "c_203": {
        "x": 126.000053406,
        "y": 43.0
      },
      "c_204": {
        "x": 85.0000534058,
        "y": 166.666671753
      },
      "c_205": {
        "x": 185.60005188,
        "y": 143.714157104
      },
      "c_206": {
        "x": 221.000045776,
        "y": 215.0
      },
      "c_207": {
        "x": 100.800048828,
        "y": 188.333328247
      },
      "c_208": {
        "x": 80.0000534058,
        "y": 231.0
      },
      "c_209": {
        "x": 36.0000495911,
        "y": 149.0
      },
      "c_21": {
        "x": 216.000045776,
        "y": 116.0
      },
      "c_210": {
        "x": 115.000053406,
        "y": 130.999969482
      },
      "c_211": {
        "x": 121.000053406,
        "y": 28.0
      },
      "c_212": {
        "x": 246.000045776,
        "y": 161.0
      },
      "c_213": {
        "x": 168.526367188,
        "y": 100.0
      },
      "c_214": {
        "x": 145.466720581,
        "y": 216.250045776
      },
      "c_215": {
        "x": 108.500053406,
        "y": 28.0000495911
      },
      "c_216": {
        "x": 23.0000495911,
        "y": 191.0
      },
      "c_217": {
        "x": 205.000045776,
        "y": 224.000045776
      },
      "c_218": {
        "x": 98.3333816528,
        "y": 132.499954224
      },
      "c_219": {
        "x": 200.000045776,
        "y": 172.000198364
      },
      "c_22": {
        "x": 153.500045776,
        "y": 213.833328247
      },
      "c_220": {
        "x": 28.0000495911,
        "y": 89.0
      },
      "c_221": {
        "x": 202.000045776,
        "y": 202.143035889
      },
      "c_222": {
        "x": 51.5000495911,
        "y": 204.0
      },
      "c_223": {
        "x": 124.200050354,
        "y": 169.0
      },
      "c_224": {
        "x": 162.000045776,
        "y": 108.0
      },
      "c_225": {
        "x": 199.000045776,
        "y": 190.0
      },
      "c_226": {
        "x": 107.000053406,
        "y": 234.375350952
      },
      "c_227": {
        "x": 203.000045776,
        "y": 72.0
      },
      "c_228": {
        "x": 110.000053406,
        "y": 56.0
      },
      "c_229": {
        "x": 181.000045776,
        "y": 235.500045776
      },
      "c_23": {
        "x": 140.466720581,
        "y": 222.249847412
      },
      "c_230": {
        "x": 173.500045776,
        "y": 61.0
      },
      "c_231": {
        "x": 95.7500534058,
        "y": 199.374649048
      },
      "c_232": {
        "x": 74.5000534058,
        "y": 56.0
      },
      "c_233": {
        "x": 113.000053406,
        "y": 136.000076294
      },
      "c_234": {
        "x": 260.000061035,
        "y": 177.0
      },
      "c_235": {
        "x": 239.000045776,
        "y": 91.0
      },
      "c_236": {
        "x": 78.0000534058,
        "y": 211.499954224
      },
      "c_237": {
        "x": 68.5714797974,
        "y": 151.0
      },
      "c_238": {
        "x": 175.500045776,
        "y": 106.000053406
      },
      "c_239": {
        "x": 243.000045776,
        "y": 180.0
      },
      "c_24": {
        "x": 161.000045776,
        "y": 49.0000495911
      },
      "c_240": {
        "x": 99.0000534058,
        "y": 243.500045776
      },
      "c_241": {
        "x": 93.0000534058,
        "y": 94.0000534058
      },
      "c_242": {
        "x": 131.750045776,
        "y": 132.0
      },
      "c_243": {
        "x": 36.0000495911,
        "y": 91.0
      },
      "c_244": {
        "x": 175.466720581,
        "y": 222.0
      },
      "c_245": {
        "x": 116.000053406,
        "y": 250.333236694
      },
      "c_246": {
        "x": 151.500045776,
        "y": 171.0
      },
      "c_247": {
        "x": 104.909141541,
        "y": 102.0
      },
      "c_248": {
        "x": 194.750045776,
        "y": 178.999954224
      },
      "c_249": {
        "x": 129.000045776,
        "y": 77.5713577271
      },
      "c_25": {
        "x": 156.000045776,
        "y": 21.5000495911
      },
      "c_250": {
        "x": 25.3333835602,
        "y": 141.0
      },
      "c_251": {
        "x": 108.333381653,
        "y": 130.999969482
      },
      "c_252": {
        "x": 151.500045776,
        "y": 265.0
      },
      "c_253": {
        "x": 106.000053406,
        "y": 156.714263916
      },
      "c_254": {
        "x": 88.5714797974,
        "y": 151.0
      },
      "c_255": {
        "x": 23.0000495911,
        "y": 130.0
      },
      "c_256": {
        "x": 176.500045776,
        "y": 216.666763306
      },
      "c_257": {
        "x": 143.000045776,
        "y": 227.249954224
      },
      "c_258": {
        "x": 268.500061035,
        "y": 125.0
      },
      "c_259": {
        "x": 209.000045776,
        "y": 84.0
      },
      "c_26": {
        "x": 180.466720581,
        "y": 223.999954224
      },
      "c_260": {
        "x": 180.000045776,
        "y": 76.0
      },
      "c_261": {
        "x": 147.60005188,
        "y": 142.0
      },
      "c_262": {
        "x": 174.000045776,
        "y": 245.999954224
      },
      "c_263": {
        "x": 93.7500534058,
        "y": 71.0
      },
      "c_264": {
        "x": 90.0000534058,
        "y": 189.285614014
      },
      "c_265": {
        "x": 41.0000495911,
        "y": 223.0
      },
      "c_266": {
        "x": 203.500045776,
        "y": 103.0
      },
      "c_267": {
        "x": 140.000045776,
        "y": 186.999847412
      },
      "c_268": {
        "x": 158.333389282,
        "y": 85.0
      },
      "c_269": {
        "x": 237.000045776,
        "y": 162.666519165
      },
      "c_27": {
        "x": 220.666717529,
        "y": 170.0
      },
      "c_270": {
        "x": 197.000045776,
        "y": 76.0
      },
      "c_271": {
        "x": 111.000053406,
        "y": 166.71446228
      },
      "c_272": {
        "x": 227.000045776,
        "y": 106.333435059
      },
      "c_273": {
        "x": 98.5714797974,
        "y": 154.0
      },
      "c_274": {
        "x": 30.5000495911,
        "y": 73.0
      },
      "c_275": {
        "x": 231.333389282,
        "y": 182.666915894
      },
      "c_276": {
        "x": 49.0000495911,
        "y": 113.499946594
      },
      "c_277": {
        "x": 221.000045776,
        "y": 119.0
      },
      "c_278": {
        "x": 41.0000495911,
        "y": 149.999847412
      },
      "c_279": {
        "x": 113.000053406,
        "y": 69.0
      },
      "c_28": {
        "x": 158.000045776,
        "y": 180.0
      },
      "c_280": {
        "x": 261.000061035,
        "y": 149.0
      },
      "c_281": {
        "x": 165.466720581,
        "y": 226.499954224
      },
      "c_282": {
        "x": 217.000045776,
        "y": 191.0
      },
      "c_283": {
        "x": 257.000061035,
        "y": 154.749923706
      },
      "c_284": {
        "x": 224.000045776,
        "y": 101.333335876
      },
      "c_285": {
        "x": 181.000045776,
        "y": 258.0
      },
      "c_286": {
        "x": 187.000045776,
        "y": 44.0
      },
      "c_287": {
        "x": 70.0000534058,
        "y": 84.0
      },
      "c_288": {
        "x": 146.500045776,
        "y": 171.0
      },
      "c_289": {
        "x": 110.000053406,
        "y": 141.000167847
      },
      "c_29": {
        "x": 133.000045776,
        "y": 109.0
      },
      "c_290": {
        "x": 246.500045776,
        "y": 196.0
      },
      "c_291": {
        "x": 127.000053406,
        "y": 156.0
      },
      "c_292": {
        "x": 117.333381653,
        "y": 144.0
      },
      "c_293": {
        "x": 127.000053406,
        "y": 103.0
      },
      "c_294": {
        "x": 94.0000534058,
        "y": 263.500061035
      },
      "c_295": {
        "x": 199.000045776,
        "y": 184.000045776
      },
      "c_296": {
        "x": 90.5000534058,
        "y": 141.0
      },
      "c_297": {
        "x": 154.000045776,
        "y": 232.0
      },
      "c_298": {
        "x": 52.0000495911,
        "y": 164.0
      },
      "c_299": {
        "x": 185.000045776,
        "y": 161.0
      },
      "c_3": {
        "x": 62.0000495911,
        "y": 110.499946594
      },
      "c_30": {
        "x": 218.000045776,
        "y": 83.0000534058
      },
      "c_300": {
        "x": 186.000045776,
        "y": 77.0000534058
      },
      "c_301": {
        "x": 114.000053406,
        "y": 202.000045776
      },
      "c_302": {
        "x": 94.0000534058,
        "y": 109.750053406
      },
      "c_303": {
        "x": 86.0000534058,
        "y": 237.499954224
      },
      "c_304": {
        "x": 213.000045776,
        "y": 225.0
      },
      "c_305": {
        "x": 37.0000495911,
        "y": 133.0
      },
      "c_306": {
        "x": 35.3333816528,
        "y": 141.0
      },
      "c_307": {
        "x": 54.0000495911,
        "y": 59.0000495911
      },
      "c_308": {
        "x": 103.000053406,
        "y": 64.0
      },
      "c_309": {
        "x": 141.000045776,
        "y": 120.842643738
      },
      "c_31": {
        "x": 239.000045776,
        "y": 107.999923706
      },
      "c_310": {
        "x": 72.0000534058,
        "y": 158.0
      },
      "c_311": {
        "x": 98.7500534058,
        "y": 75.0
      },
      "c_312": {
        "x": 112.000053406,
        "y": 237.0
      },
      "c_313": {
        "x": 139.000045776,
        "y": 212.0
      },
      "c_314": {
        "x": 108.000053406,
        "y": 85.0
      },
      "c_315": {
        "x": 83.0000534058,
        "y": 253.0
      },
      "c_316": {
        "x": 56.0000495911,
        "y": 226.499954224
      },
      "c_317": {
        "x": 176.000045776,
        "y": 39.0
      },
      "c_318": {
        "x": 117.000053406,
        "y": 260.333435059
      },
      "c_319": {
        "x": 142.60005188,
        "y": 145.0
      },
      "c_32": {
        "x": 105.000053406,
        "y": 224.375152588
      },
      "c_320": {
        "x": 101.000053406,
        "y": 193.333435059
      },
      "c_321": {
        "x": 148.000045776,
        "y": 206.249847412
      },
      "c_322": {
        "x": 52.0000495911,
        "y": 95.6667633057
      },
      "c_323": {
        "x": 135.500045776,
        "y": 238.0
      },
      "c_324": {
        "x": 234.000045776,
        "y": 81.4999465942
      },
      "c_325": {
        "x": 102.000053406,
        "y": 42.0
      },
      "c_326": {
        "x": 133.000045776,
        "y": 209.499954224
      },
      "c_327": {
        "x": 213.666717529,
        "y": 91.9999465942
      },
      "c_328": {
        "x": 37.0000495911,
        "y": 172.0
      },
      "c_329": {
        "x": 226.333389282,
        "y": 196.0
      },
      "c_33": {
        "x": 156.000045776,
        "y": 241.599853516
      },
      "c_330": {
        "x": 25.0000495911,
        "y": 177.999954224
      },
      "c_331": {
        "x": 167.000045776,
        "y": 231.500045776
      },
      "c_332": {
        "x": 105.750053406,
        "y": 204.0
      },
      "c_333": {
        "x": 256.500061035,
        "y": 190.0
      },
      "c_334": {
        "x": 106.000053406,
        "y": 22.9999504089
      },
      "c_335": {
        "x": 192.333389282,
        "y": 106.999847412
      },
      "c_336": {
        "x": 30.0000495911,
        "y": 156.000045776
      },
      "c_337": {
        "x": 133.666717529,
        "y": 268.0
      },
      "c_338": {
        "x": 183.000045776,
        "y": 49.9999504089
      },
      "c_339": {
        "x": 88.6667175293,
        "y": 107.666763306
      },
      "c_34": {
        "x": 117.166717529,
        "y": 196.999893188
      },
      "c_340": {
        "x": 76.4000473022,
        "y": 174.0
      },
      "c_341": {
        "x": 122.000053406,
        "y": 76.0
      },
      "c_342": {
        "x": 85.0000534058,
        "y": 97.6665649414
      },
      "c_343": {
        "x": 250.000045776,
        "y": 171.0
      },
      "c_344": {
        "x": 194.000045776,
        "y": 45.5000495911
      },
      "c_345": {
        "x": 216.800048828,
        "y": 156.0
      },
      "c_346": {
        "x": 47.0000495911,
        "y": 68.0
      },
      "c_347": {
        "x": 65.0000534058,
        "y": 115.500053406
      },
      "c_348": {
        "x": 253.000045776,
        "y": 125.999900818
      },
      "c_349": {
        "x": 56.0000495911,
        "y": 247.0
      },
      "c_35": {
        "x": 73.5714797974,
        "y": 151.0
      },
      "c_350": {
        "x": 184.200042725,
        "y": 116.0
      },
      "c_351": {
        "x": 205.666717529,
        "y": 111.333084106
      },
      "c_352": {
        "x": 90.0000534058,
        "y": 162.0
      },
      "c_353": {
        "x": 139.000045776,
        "y": 69.3334350586
      },
      "c_354": {
        "x": 94.5000534058,
        "y": 114.750152588
      },
      "c_355": {
        "x": 112.000053406,
        "y": 61.0000991821
      },
      "c_356": {
        "x": 66.4000473022,
        "y": 172.0
      },
      "c_357": {
        "x": 101.000053406,
        "y": 143.0
      },
      "c_358": {
        "x": 123.000053406,
        "y": 225.599899292
      },
      "c_359": {
        "x": 24.0000495911,
        "y": 163.0
      },
      "c_36": {
        "x": 37.0000495911,
        "y": 111.999946594
      },
      "c_360": {
        "x": 112.000053406,
        "y": 41.0000495911
      },
      "c_361": {
        "x": 241.000045776,
        "y": 157.666412354
      },
      "c_362": {
        "x": 181.000045776,
        "y": 95.0
      },
      "c_363": {
        "x": 181.000045776,
        "y": 179.499893188
      },
      "c_364": {
        "x": 203.000045776,
        "y": 139.166915894
      },
      "c_365": {
        "x": 221.333389282,
        "y": 183.999954224
      },
      "c_366": {
        "x": 142.500045776,
        "y": 162.999954224
      },
      "c_367": {
        "x": 215.666717529,
        "y": 174.0
      },
      "c_368": {
        "x": 180.000045776,
        "y": 70.0
      },
      "c_369": {
        "x": 168.333389282,
        "y": 84.9999160767
      },
      "c_37": {
        "x": 87.0000534058,
        "y": 102.666664124
      },
      "c_370": {
        "x": 80.8889389038,
        "y": 120.0
      },
      "c_371": {
        "x": 63.5714797974,
        "y": 154.0
      },
      "c_372": {
        "x": 123.333381653,
        "y": 70.9999008179
      },
      "c_373": {
        "x": 242.000045776,
        "y": 52.0
      },
      "c_374": {
        "x": 226.800048828,
        "y": 161.0
      },
      "c_375": {
        "x": 174.000045776,
        "y": 257.999908447
      },
      "c_376": {
        "x": 139.000045776,
        "y": 191.999954224
      },
      "c_377": {
        "x": 219.000045776,
        "y": 71.0
      },
      "c_378": {
        "x": 263.000061035,
        "y": 183.0
      },
      "c_379": {
        "x": 88.7500534058,
        "y": 73.0
      },
      "c_38": {
        "x": 60.4000511169,
        "y": 190.0
      },
      "c_380": {
        "x": 46.0000495911,
        "y": 141.0
      },
      "c_381": {
        "x": 189.000045776,
        "y": 71.9999465942
      },
      "c_382": {
        "x": 50.4000511169,
        "y": 188.0
      },
      "c_383": {
        "x": 201.000045776,
        "y": 64.0000534058
      },
      "c_384": {
        "x": 193.000045776,
        "y": 40.4999504089
      },
      "c_385": {
        "x": 47.0000495911,
        "y": 161.0
      },
      "c_386": {
        "x": 178.500045776,
        "y": 62.0
      },
      "c_387": {
        "x": 230.000045776,
        "y": 47.0
      },
      "c_388": {
        "x": 222.000045776,
        "y": 41.0
      },
      "c_389": {
        "x": 226.000045776,
        "y": 214.0
      },
      "c_39": {
        "x": 265.000061035,
        "y": 207.0
      },
      "c_390": {
        "x": 69.0000534058,
        "y": 194.0
      },
      "c_391": {
        "x": 109.000053406,
        "y": 125.99987793
      },
      "c_392": {
        "x": 184.000045776,
        "y": 55.0000495911
      },
      "c_393": {
        "x": 199.000045776,
        "y": 197.142944336
      },
      "c_394": {
        "x": 232.666717529,
        "y": 189.999954224
      },
      "c_395": {
        "x": 101.000053406,
        "y": 238.499954224
      },
      "c_396": {
        "x": 83.3333816528,
        "y": 218.0
      },
      "c_397": {
        "x": 208.000045776,
        "y": 58.0000343323
      },
      "c_398": {
        "x": 160.466720581,
        "y": 223.999954224
      },
      "c_399": {
        "x": 188.666717529,
        "y": 135.500045776
      },
      "c_4": {
        "x": 173.000045776,
        "y": 124.0
      },
      "c_40": {
        "x": 138.666717529,
        "y": 266.0
      },
      "c_400": {
        "x": 127.000053406,
        "y": 64.0000991821
      },
      "c_401": {
        "x": 184.60005188,
        "y": 126.0
      },
      "c_402": {
        "x": 148.333389282,
        "y": 156.0
      },
      "c_403": {
        "x": 247.000045776,
        "y": 115.0
      },
      "c_404": {
        "x": 59.0000495911,
        "y": 231.500045776
      },
      "c_405": {
        "x": 231.000045776,
        "y": 136.749847412
      },
      "c_406": {
        "x": 201.000045776,
        "y": 216.0
      },
      "c_407": {
        "x": 158.526367188,
        "y": 100.000213623
      },
      "c_408": {
        "x": 141.000045776,
        "y": 151.0
      },
      "c_409": {
        "x": 235.000045776,
        "y": 118.00012207
      },
      "c_41": {
        "x": 229.000045776,
        "y": 237.0
      },
      "c_410": {
        "x": 28.0000495911,
        "y": 133.333435059
      },
      "c_411": {
        "x": 213.500045776,
        "y": 97.0000534058
      },
      "c_412": {
        "x": 211.000045776,
        "y": 238.0
      },
      "c_413": {
        "x": 114.000053406,
        "y": 81.0000534058
      },
      "c_414": {
        "x": 119.909141541,
        "y": 94.0
      },
      "c_415": {
        "x": 195.000045776,
        "y": 53.4999504089
      },
      "c_416": {
        "x": 135.000045776,
        "y": 93.0000534058
      },
      "c_417": {
        "x": 189.000045776,
        "y": 234.000045776
      },
      "c_418": {
        "x": 80.0000534058,
        "y": 32.0
      },
      "c_419": {
        "x": 237.60005188,
        "y": 129.0
      },
      "c_42": {
        "x": 38.0000495911,
        "y": 165.000152588
      },
      "c_420": {
        "x": 103.000053406,
        "y": 219.375045776
      },
      "c_421": {
        "x": 198.500045776,
        "y": 103.0
      },
      "c_422": {
        "x": 246.000045776,
        "y": 209.500045776
      },
      "c_423": {
        "x": 249.000045776,
        "y": 120.000099182
      },
      "c_424": {
        "x": 55.4000511169,
        "y": 188.0
      },
      "c_425": {
        "x": 239.000045776,
        "y": 167.666610718
      },
      "c_426": {
        "x": 155.466720581,
        "y": 223.833526611
      },
      "c_427": {
        "x": 123.000053406,
        "y": 81.0000991821
      },
      "c_428": {
        "x": 55.8889389038,
        "y": 133.0
      },
      "c_429": {
        "x": 107.000053406,
        "y": 41.0
      },
      "c_43": {
        "x": 148.000045776,
        "y": 75.0000991821
      },
      "c_430": {
        "x": 50.8889389038,
        "y": 118.500053406
      },
      "c_431": {
        "x": 130.000045776,
        "y": 214.500045776
      },
      "c_432": {
        "x": 231.250045776,
        "y": 206.0
      },
      "c_433": {
        "x": 129.909133911,
        "y": 97.0
      },
      "c_434": {
        "x": 158.500045776,
        "y": 246.599960327
      },
      "c_435": {
        "x": 153.526367188,
        "y": 95.8421401978
      },
      "c_436": {
        "x": 21.0000495911,
        "y": 183.000045776
      },
      "c_437": {
        "x": 222.000045776,
        "y": 108.499946594
      },
      "c_438": {
        "x": 132.500045776,
        "y": 249.0
      },
      "c_439": {
        "x": 109.909141541,
        "y": 95.0
      },
      "c_44": {
        "x": 221.250045776,
        "y": 204.0
      },
      "c_440": {
        "x": 133.333389282,
        "y": 72.5712585449
      },
      "c_441": {
        "x": 239.250045776,
        "y": 147.500045776
      },
      "c_442": {
        "x": 93.5714797974,
        "y": 147.0
      },
      "c_443": {
        "x": 184.000045776,
        "y": 243.499954224
      },
      "c_444": {
        "x": 242.500045776,
        "y": 135.0
      },
      "c_445": {
        "x": 146.000045776,
        "y": 81.599899292
      },
      "c_446": {
        "x": 142.000045776,
        "y": 197.000045776
      },
      "c_447": {
        "x": 225.000045776,
        "y": 189.000045776
      },
      "c_448": {
        "x": 86.4000473022,
        "y": 171.666763306
      },
      "c_449": {
        "x": 208.500045776,
        "y": 209.0
      },
      "c_45": {
        "x": 162.000045776,
        "y": 256.0
      },
      "c_450": {
        "x": 163.000045776,
        "y": 203.0
      },
      "c_451": {
        "x": 268.000061035,
        "y": 188.0
      },
      "c_452": {
        "x": 40.0000495911,
        "y": 123.0
      },
      "c_453": {
        "x": 138.526367188,
        "y": 82.5714569092
      },
      "c_454": {
        "x": 103.000053406,
        "y": 214.374954224
      },
      "c_455": {
        "x": 189.000045776,
        "y": 185.999893188
      },
      "c_456": {
        "x": 107.000053406,
        "y": 172.0
      },
      "c_457": {
        "x": 161.000045776,
        "y": 261.000091553
      },
      "c_458": {
        "x": 113.000053406,
        "y": 220.999954224
      },
      "c_459": {
        "x": 231.000045776,
        "y": 146.750045776
      },
      "c_46": {
        "x": 89.0000534058,
        "y": 199.285812378
      },
      "c_460": {
        "x": 72.0000534058,
        "y": 90.0
      },
      "c_461": {
        "x": 58.5714797974,
        "y": 152.0
      },
      "c_462": {
        "x": 173.000045776,
        "y": 47.0
      },
      "c_463": {
        "x": 61.0000495911,
        "y": 218.0
      },
      "c_464": {
        "x": 263.500061035,
        "y": 122.0
      },
      "c_465": {
        "x": 114.909141541,
        "y": 96.3332366943
      },
      "c_466": {
        "x": 125.466712952,
        "y": 230.600006104
      },
      "c_467": {
        "x": 159.400054932,
        "y": 60.8414421082
      },
      "c_468": {
        "x": 229.000045776,
        "y": 62.5000495911
      },
      "c_469": {
        "x": 119.200050354,
        "y": 173.0
      },
      "c_47": {
        "x": 110.000053406,
        "y": 249.500045776
      },
      "c_470": {
        "x": 109.000053406,
        "y": 79.0
      },
      "c_471": {
        "x": 172.000045776,
        "y": 206.666564941
      },
      "c_472": {
        "x": 49.0000495911,
        "y": 131.0
      },
      "c_473": {
        "x": 109.909141541,
        "y": 101.0
      },
      "c_474": {
        "x": 165.000045776,
        "y": 90.0000152588
      },
      "c_475": {
        "x": 203.000045776,
        "y": 151.0
      },
      "c_476": {
        "x": 95.0000534058,
        "y": 226.999893188
      },
      "c_477": {
        "x": 147.000045776,
        "y": 115.842544556
      },
      "c_478": {
        "x": 84.0000534058,
        "y": 242.500045776
      },
      "c_479": {
        "x": 244.000045776,
        "y": 204.499954224
      },
      "c_48": {
        "x": 125.500053406,
        "y": 241.0
      },
      "c_480": {
        "x": 251.500045776,
        "y": 192.0
      },
      "c_481": {
        "x": 100.888938904,
        "y": 117.499946594
      },
      "c_482": {
        "x": 209.000045776,
        "y": 192.142837524
      },
      "c_483": {
        "x": 45.0000495911,
        "y": 232.499954224
      },
      "c_484": {
        "x": 169.000045776,
        "y": 217.000045776
      },
      "c_485": {
        "x": 120.500053406,
        "y": 240.500045776
      },
      "c_486": {
        "x": 180.666717529,
        "y": 195.0
      },
      "c_487": {
        "x": 179.000045776,
        "y": 158.71446228
      },
      "c_488": {
        "x": 209.750045776,
        "y": 182.14263916
      },
      "c_489": {
        "x": 39.0000495911,
        "y": 199.0
      },
      "c_49": {
        "x": 155.000045776,
        "y": 70.8416442871
      },
      "c_490": {
        "x": 178.526367188,
        "y": 100.000099182
      },
      "c_491": {
        "x": 225.000045776,
        "y": 221.0
      },
      "c_492": {
        "x": 167.000045776,
        "y": 140.0
      },
      "c_493": {
        "x": 197.000045776,
        "y": 144.0
      },
      "c_494": {
        "x": 66.0000534058,
        "y": 210.0
      },
      "c_495": {
        "x": 221.800048828,
        "y": 159.0
      },
      "c_496": {
        "x": 208.666717529,
        "y": 91.0
      },
      "c_497": {
        "x": 185.000045776,
        "y": 89.0
      },
      "c_498": {
        "x": 242.60005188,
        "y": 128.0
      },
      "c_499": {
        "x": 127.166717529,
        "y": 194.0
      },
      "c_5": {
        "x": 95.0000534058,
        "y": 41.0
      },
      "c_50": {
        "x": 119.000053406,
        "y": 125.99987793
      },
      "c_500": {
        "x": 196.000045776,
        "y": 241.500045776
      },
      "c_501": {
        "x": 83.6667175293,
        "y": 109.499946594
      },
      "c_502": {
        "x": 144.000045776,
        "y": 232.250045776
      },
      "c_503": {
        "x": 220.000045776,
        "y": 53.0
      },
      "c_504": {
        "x": 163.000045776,
        "y": 190.333435059
      },
      "c_505": {
        "x": 138.526367188,
        "y": 87.5715560913
      },
      "c_506": {
        "x": 129.000045776,
        "y": 121.0
      },
      "c_507": {
        "x": 190.466720581,
        "y": 217.0
      },
      "c_508": {
        "x": 45.0000495911,
        "y": 121.0
      },
      "c_509": {
        "x": 183.000045776,
        "y": 133.0
      },
      "c_51": {
        "x": 130.000045776,
        "y": 150.333435059
      },
      "c_510": {
        "x": 143.526367188,
        "y": 86.5999984741
      },
      "c_511": {
        "x": 15.3333835602,
        "y": 142.0
      },
      "c_512": {
        "x": 200.666717529,
        "y": 114.166419983
      },
      "c_513": {
        "x": 120.000053406,
        "y": 49.0
      },
      "c_514": {
        "x": 195.500045776,
        "y": 258.0
      },
      "c_515": {
        "x": 235.000045776,
        "y": 67.0
      },
      "c_516": {
        "x": 178.000045776,
        "y": 113.0
      },
      "c_517": {
        "x": 208.500045776,
        "y": 99.0
      },
      "c_518": {
        "x": 155.000045776,
        "y": 75.8417434692
      },
      "c_519": {
        "x": 67.0000534058,
        "y": 180.800125122
      },
      "c_52": {
        "x": 70.8889389038,
        "y": 122.0
      },
      "c_520": {
        "x": 211.000045776,
        "y": 215.0
      },
      "c_521": {
        "x": 227.60005188,
        "y": 131.0
      },
      "c_522": {
        "x": 192.333389282,
        "y": 101.0
      },
      "c_523": {
        "x": 222.60005188,
        "y": 131.0
      },
      "c_524": {
        "x": 128.666717529,
        "y": 269.0
      },
      "c_525": {
        "x": 142.000045776,
        "y": 126.0
      },
      "c_526": {
        "x": 201.000045776,
        "y": 167.000106812
      },
      "c_527": {
        "x": 236.333389282,
        "y": 195.000045776
      },
      "c_528": {
        "x": 239.250045776,
        "y": 142.499954224
      },
      "c_529": {
        "x": 59.0000495911,
        "y": 103.0
      },
      "c_53": {
        "x": 30.3333835602,
        "y": 139.499954224
      },
      "c_530": {
        "x": 189.000045776,
        "y": 65.0
      },
      "c_531": {
        "x": 208.000045776,
        "y": 148.0
      },
      "c_532": {
        "x": 185.466720581,
        "y": 221.0
      },
      "c_533": {
        "x": 171.000045776,
        "y": 117.0
      },
      "c_534": {
        "x": 153.000045776,
        "y": 121.999946594
      },
      "c_535": {
        "x": 115.000053406,
        "y": 75.9999465942
      },
      "c_536": {
        "x": 209.500045776,
        "y": 139.0
      },
      "c_537": {
        "x": 217.000045776,
        "y": 144.0
      },
      "c_538": {
        "x": 153.000045776,
        "y": 197.0
      },
      "c_539": {
        "x": 132.166717529,
        "y": 191.0
      },
      "c_54": {
        "x": 59.0000495911,
        "y": 162.500045776
      },
      "c_540": {
        "x": 55.0000495911,
        "y": 178.0
      },
      "c_541": {
        "x": 144.400054932,
        "y": 64.9999008179
      },
      "c_542": {
        "x": 143.526367188,
        "y": 91.6000976562
      },
      "c_543": {
        "x": 200.000045776,
        "y": 250.0
      },
      "c_544": {
        "x": 231.000045776,
        "y": 213.000045776
      },
      "c_545": {
        "x": 94.0000534058,
        "y": 81.0
      },
      "c_546": {
        "x": 152.000045776,
        "y": 80.8418426514
      },
      "c_547": {
        "x": 73.3333816528,
        "y": 131.0
      },
      "c_548": {
        "x": 75.3333816528,
        "y": 186.0
      },
      "c_549": {
        "x": 159.000045776,
        "y": 43.9999504089
      },
      "c_55": {
        "x": 200.000045776,
        "y": 162.0
      },
      "c_550": {
        "x": 180.500045776,
        "y": 105.000198364
      },
      "c_551": {
        "x": 65.8889389038,
        "y": 124.0
      },
      "c_552": {
        "x": 186.000045776,
        "y": 201.999954224
      },
      "c_553": {
        "x": 169.000045776,
        "y": 108.0
      },
      "c_554": {
        "x": 138.000045776,
        "y": 59.3332328796
      },
      "c_555": {
        "x": 188.000045776,
        "y": 179.0
      },
      "c_556": {
        "x": 79.5000534058,
        "y": 58.0
      },
      "c_557": {
        "x": 67.0000534058,
        "y": 110.0
      },
      "c_558": {
        "x": 199.750045776,
        "y": 178.0
      },
      "c_559": {
        "x": 229.000045776,
        "y": 141.749954224
      },
      "c_56": {
        "x": 81.4000473022,
        "y": 173.0
      },
      "c_560": {
        "x": 99.0000534058,
        "y": 81.9999465942
      },
      "c_561": {
        "x": 124.909141541,
        "y": 95.0
      },
      "c_562": {
        "x": 110.800048828,
        "y": 187.0
      },
      "c_563": {
        "x": 235.000045776,
        "y": 153.0
      },
      "c_564": {
        "x": 100.000053406,
        "y": 50.0
      },
      "c_565": {
        "x": 164.000045776,
        "y": 79.9998092651
      },
      "c_566": {
        "x": 134.000045776,
        "y": 126.0
      },
      "c_567": {
        "x": 120.000053406,
        "y": 155.0
      },
      "c_568": {
        "x": 173.000045776,
        "y": 251.000045776
      },
      "c_569": {
        "x": 41.0000495911,
        "y": 141.0
      },
      "c_57": {
        "x": 135.466720581,
        "y": 224.0
      },
      "c_570": {
        "x": 203.666717529,
        "y": 90.0
      },
      "c_571": {
        "x": 96.4000473022,
        "y": 177.0
      },
      "c_572": {
        "x": 161.500045776,
        "y": 168.999954224
      },
      "c_573": {
        "x": 250.000045776,
        "y": 178.0
      },
      "c_574": {
        "x": 162.000045776,
        "y": 185.333328247
      },
      "c_575": {
        "x": 206.000045776,
        "y": 42.0
      },
      "c_576": {
        "x": 46.5000495911,
        "y": 201.0
      },
      "c_577": {
        "x": 138.500045776,
        "y": 44.0
      },
      "c_578": {
        "x": 233.000045776,
        "y": 95.0
      },
      "c_579": {
        "x": 72.0000534058,
        "y": 104.0
      },
      "c_58": {
        "x": 251.000045776,
        "y": 154.749923706
      },
      "c_580": {
        "x": 113.500053406,
        "y": 25.0
      },
      "c_581": {
        "x": 107.000053406,
        "y": 229.375244141
      },
      "c_582": {
        "x": 194.000045776,
        "y": 204.000045776
      },
      "c_583": {
        "x": 228.000045776,
        "y": 120.0
      },
      "c_584": {
        "x": 45.4000511169,
        "y": 193.0
      },
      "c_585": {
        "x": 129.000045776,
        "y": 235.600097656
      },
      "c_586": {
        "x": 158.000045776,
        "y": 191.999954224
      },
      "c_587": {
        "x": 136.000045776,
        "y": 120.842643738
      },
      "c_588": {
        "x": 173.000045776,
        "y": 133.0
      },
      "c_589": {
        "x": 119.000053406,
        "y": 219.0
      },
      "c_59": {
        "x": 61.0000495911,
        "y": 174.0
      },
      "c_590": {
        "x": 20.3333835602,
        "y": 143.0
      },
      "c_591": {
        "x": 190.500045776,
        "y": 258.0
      },
      "c_592": {
        "x": 158.000045776,
        "y": 128.0
      },
      "c_593": {
        "x": 29.0000495911,
        "y": 122.0
      },
      "c_594": {
        "x": 83.5000534058,
        "y": 199.0
      },
      "c_595": {
        "x": 167.000045776,
        "y": 73.0000534058
      },
      "c_596": {
        "x": 194.200042725,
        "y": 117.000053406
      },
      "c_597": {
        "x": 83.3333816528,
        "y": 131.0
      },
      "c_598": {
        "x": 100.888938904,
        "y": 122.500053406
      },
      "c_599": {
        "x": 172.333389282,
        "y": 68.0
      },
      "c_6": {
        "x": 132.000045776,
        "y": 161.500045776
      },
      "c_60": {
        "x": 115.888938904,
        "y": 113.999946594
      },
      "c_600": {
        "x": 103.750053406,
        "y": 74.0
      },
      "c_601": {
        "x": 220.000045776,
        "y": 150.0
      },
      "c_602": {
        "x": 62.0000495911,
        "y": 55.0
      },
      "c_603": {
        "x": 155.000045776,
        "y": 36.0
      },
      "c_604": {
        "x": 196.000045776,
        "y": 58.5000495911
      },
      "c_605": {
        "x": 47.0000495911,
        "y": 218.0
      },
      "c_606": {
        "x": 101.400047302,
        "y": 172.999954224
      },
      "c_607": {
        "x": 104.909141541,
        "y": 92.0
      },
      "c_608": {
        "x": 80.0000534058,
        "y": 160.000045776
      },
      "c_609": {
        "x": 140.000045776,
        "y": 254.0
      },
      "c_61": {
        "x": 149.400054932,
        "y": 64.0
      },
      "c_610": {
        "x": 126.000053406,
        "y": 220.59979248
      },
      "c_611": {
        "x": 162.000045776,
        "y": 72.0000991821
      },
      "c_612": {
        "x": 105.888938904,
        "y": 116.0
      },
      "c_613": {
        "x": 205.000045776,
        "y": 233.999954224
      },
      "c_614": {
        "x": 138.000045776,
        "y": 115.842544556
      },
      "c_615": {
        "x": 78.5000534058,
        "y": 201.0
      },
      "c_616": {
        "x": 172.000045776,
        "y": 263.0
      },
      "c_617": {
        "x": 126.000053406,
        "y": 130.0
      },
      "c_618": {
        "x": 187.500045776,
        "y": 207.000045776
      },
      "c_619": {
        "x": 254.000045776,
        "y": 131.0
      },
      "c_62": {
        "x": 133.526367188,
        "y": 87.9999465942
      },
      "c_620": {
        "x": 159.000045776,
        "y": 229.000045776
      },
      "c_621": {
        "x": 127.500053406,
        "y": 248.0
      },
      "c_622": {
        "x": 233.000045776,
        "y": 86.5000534058
      },
      "c_623": {
        "x": 54.0000495911,
        "y": 85.6665649414
      },
      "c_624": {
        "x": 171.000045776,
        "y": 167.0
      },
      "c_625": {
        "x": 213.000045776,
        "y": 251.0
      },
      "c_626": {
        "x": 241.500045776,
        "y": 198.0
      },
      "c_627": {
        "x": 73.0000534058,
        "y": 180.800125122
      },
      "c_628": {
        "x": 186.000045776,
        "y": 166.499954224
      },
      "c_629": {
        "x": 251.000045776,
        "y": 109.999900818
      },
      "c_63": {
        "x": 129.000045776,
        "y": 145.333328247
      },
      "c_630": {
        "x": 213.000045776,
        "y": 70.0
      },
      "c_631": {
        "x": 149.000045776,
        "y": 236.0
      },
      "c_632": {
        "x": 269.000061035,
        "y": 140.999954224
      },
      "c_633": {
        "x": 67.0000534058,
        "y": 230.666564941
      },
      "c_634": {
        "x": 130.466720581,
        "y": 226.0
      },
      "c_635": {
        "x": 157.60005188,
        "y": 140.0
      },
      "c_636": {
        "x": 187.333389282,
        "y": 103.999946594
      },
      "c_637": {
        "x": 71.0000534058,
        "y": 49.0
      },
      "c_638": {
        "x": 158.333389282,
        "y": 154.0
      },
      "c_639": {
        "x": 152.000045776,
        "y": 90.8420410156
      },
      "c_64": {
        "x": 100.800048828,
        "y": 183.333236694
      },
      "c_640": {
        "x": 72.5000534058,
        "y": 140.0
      },
      "c_641": {
        "x": 89.0000534058,
        "y": 204.285919189
      },
      "c_642": {
        "x": 78.5714797974,
        "y": 154.999954224
      },
      "c_643": {
        "x": 222.000045776,
        "y": 96.3332366943
      },
      "c_644": {
        "x": 56.0000495911,
        "y": 53.9999504089
      },
      "c_645": {
        "x": 68.0000534058,
        "y": 38.0
      },
      "c_646": {
        "x": 39.0000495911,
        "y": 154.999954224
      },
      "c_647": {
        "x": 232.60005188,
        "y": 128.0
      },
      "c_648": {
        "x": 221.000045776,
        "y": 231.0
      },
      "c_649": {
        "x": 135.000045776,
        "y": 218.0
      },
      "c_65": {
        "x": 95.7500534058,
        "y": 204.374755859
      },
      "c_650": {
        "x": 118.000053406,
        "y": 66.0
      },
      "c_651": {
        "x": 176.500045776,
        "y": 229.000045776
      },
      "c_652": {
        "x": 208.000045776,
        "y": 116.333183289
      },
      "c_653": {
        "x": 103.333381653,
        "y": 130.0
      },
      "c_654": {
        "x": 47.0000495911,
        "y": 237.500045776
      },
      "c_655": {
        "x": 269.500061035,
        "y": 110.0
      },
      "c_656": {
        "x": 71.4000473022,
        "y": 170.799926758
      },
      "c_657": {
        "x": 96.4000473022,
        "y": 171.000045776
      },
      "c_658": {
        "x": 204.000045776,
        "y": 192.142837524
      },
      "c_659": {
        "x": 122.333381653,
        "y": 142.000045776
      },
      "c_66": {
        "x": 100.750053406,
        "y": 202.0
      },
      "c_660": {
        "x": 138.000045776,
        "y": 247.0
      },
      "c_661": {
        "x": 168.000045776,
        "y": 192.0
      },
      "c_662": {
        "x": 64.0000534058,
        "y": 199.000106812
      },
      "c_663": {
        "x": 128.333389282,
        "y": 70.0
      },
      "c_664": {
        "x": 45.4000511169,
        "y": 185.0
      },
      "c_665": {
        "x": 153.000045776,
        "y": 127.000053406
      },
      "c_666": {
        "x": 29.5000495911,
        "y": 115.0
      },
      "c_667": {
        "x": 106.000053406,
        "y": 146.714050293
      },
      "c_668": {
        "x": 67.0000534058,
        "y": 165.000045776
      },
      "c_669": {
        "x": 73.5000534058,
        "y": 205.0
      },
      "c_67": {
        "x": 207.000045776,
        "y": 203.499954224
      },
      "c_670": {
        "x": 167.333389282,
        "y": 67.9999465942
      },
      "c_671": {
        "x": 212.000045776,
        "y": 264.0
      },
      "c_672": {
        "x": 227.500045776,
        "y": 174.0
      },
      "c_673": {
        "x": 146.500045776,
        "y": 262.0
      },
      "c_674": {
        "x": 168.500045776,
        "y": 56.0000495911
      },
      "c_675": {
        "x": 145.000045776,
        "y": 105.842338562
      },
      "c_676": {
        "x": 67.0000534058,
        "y": 132.0
      },
      "c_677": {
        "x": 189.000045776,
        "y": 228.999954224
      },
      "c_678": {
        "x": 73.5000534058,
        "y": 199.500045776
      },
      "c_679": {
        "x": 230.000045776,
        "y": 57.4999504089
      },
      "c_68": {
        "x": 65.0000534058,
        "y": 159.999954224
      },
      "c_680": {
        "x": 213.000045776,
        "y": 34.0
      },
      "c_681": {
        "x": 193.666717529,
        "y": 138.0
      },
      "c_682": {
        "x": 30.0000495911,
        "y": 170.0
      },
      "c_683": {
        "x": 254.000045776,
        "y": 103.0
      },
      "c_684": {
        "x": 121.000053406,
        "y": 213.0
      },
      "c_685": {
        "x": 226.250045776,
        "y": 207.999954224
      },
      "c_686": {
        "x": 180.60005188,
        "y": 143.714157104
      },
      "c_687": {
        "x": 220.000045776,
        "y": 198.0
      },
      "c_688": {
        "x": 268.000061035,
        "y": 162.0
      },
      "c_689": {
        "x": 195.000045776,
        "y": 81.9999465942
      },
      "c_69": {
        "x": 118.526367188,
        "y": 87.0
      },
      "c_690": {
        "x": 194.60005188,
        "y": 131.0
      },
      "c_691": {
        "x": 170.466720581,
        "y": 225.0
      },
      "c_692": {
        "x": 45.0000495911,
        "y": 173.0
      },
      "c_693": {
        "x": 134.909133911,
        "y": 101.0
      },
      "c_694": {
        "x": 168.000045776,
        "y": 237.0
      },
      "c_695": {
        "x": 164.000045776,
        "y": 211.0
      },
      "c_696": {
        "x": 179.000045776,
        "y": 184.5
      },
      "c_697": {
        "x": 51.0000495911,
        "y": 148.0
      },
      "c_698": {
        "x": 153.000045776,
        "y": 16.4999504089
      },
      "c_699": {
        "x": 202.000045776,
        "y": 58.9999504089
      },
      "c_7": {
        "x": 131.000045776,
        "y": 140.333236694
      },
      "c_70": {
        "x": 225.000045776,
        "y": 78.0
      },
      "c_700": {
        "x": 118.000053406,
        "y": 207.000106812
      },
      "c_701": {
        "x": 231.333389282,
        "y": 200.0
      },
      "c_702": {
        "x": 90.0000534058,
        "y": 222.0
      },
      "c_703": {
        "x": 133.500045776,
        "y": 44.9999504089
      },
      "c_704": {
        "x": 179.000045776,
        "y": 20.0
      },
      "c_705": {
        "x": 77.5000534058,
        "y": 142.0
      },
      "c_706": {
        "x": 202.000045776,
        "y": 124.166618347
      },
      "c_707": {
        "x": 178.000045776,
        "y": 136.0
      },
      "c_708": {
        "x": 214.000045776,
        "y": 126.333381653
      },
      "c_709": {
        "x": 178.000045776,
        "y": 174.499801636
      },
      "c_71": {
        "x": 181.500045776,
        "y": 230.499954224
      },
      "c_710": {
        "x": 192.000045776,
        "y": 162.999954224
      },
      "c_711": {
        "x": 78.0000534058,
        "y": 253.000045776
      },
      "c_712": {
        "x": 185.666717529,
        "y": 191.0
      },
      "c_713": {
        "x": 232.500045776,
        "y": 177.666809082
      },
      "c_714": {
        "x": 135.000045776,
        "y": 77.5713577271
      },
      "c_715": {
        "x": 93.5714797974,
        "y": 154.0
      },
      "c_716": {
        "x": 207.000045776,
        "y": 187.142745972
      },
      "c_717": {
        "x": 190.666717529,
        "y": 191.0
      },
      "c_718": {
        "x": 154.000045776,
        "y": 111.0
      },
      "c_719": {
        "x": 170.60005188,
        "y": 148.499954224
      },
      "c_72": {
        "x": 194.000045776,
        "y": 94.0
      },
      "c_720": {
        "x": 269.000061035,
        "y": 146.000045776
      },
      "c_721": {
        "x": 164.000045776,
        "y": 119.0
      },
      "c_722": {
        "x": 29.0000495911,
        "y": 163.0
      },
      "c_723": {
        "x": 203.500045776,
        "y": 208.500045776
      },
      "c_724": {
        "x": 144.000045776,
        "y": 237.250152588
      },
      "c_725": {
        "x": 43.0000495911,
        "y": 178.000106812
      },
      "c_726": {
        "x": 93.6667175293,
        "y": 104.749946594
      },
      "c_727": {
        "x": 264.500061035,
        "y": 107.0
      },
      "c_728": {
        "x": 85.8889389038,
        "y": 121.000030518
      },
      "c_729": {
        "x": 133.000045776,
        "y": 28.0
      },
      "c_73": {
        "x": 173.526367188,
        "y": 100.999946594
      },
      "c_730": {
        "x": 30.3333835602,
        "y": 144.500045776
      },
      "c_731": {
        "x": 58.5714797974,
        "y": 157.499954224
      },
      "c_732": {
        "x": 143.000045776,
        "y": 76.5998001099
      },
      "c_733": {
        "x": 231.800048828,
        "y": 162.0
      },
      "c_734": {
        "x": 68.0000534058,
        "y": 188.999893188
      },
      "c_735": {
        "x": 216.250045776,
        "y": 205.0
      },
      "c_736": {
        "x": 250.000045776,
        "y": 95.0
      },
      "c_737": {
        "x": 74.0000534058,
        "y": 194.499954224
      },
      "c_738": {
        "x": 82.0000534058,
        "y": 66.9999465942
      },
      "c_739": {
        "x": 195.000045776,
        "y": 168.000045776
      },
      "c_74": {
        "x": 175.000045776,
        "y": 211.666671753
      },
      "c_740": {
        "x": 215.000045776,
        "y": 77.9999465942
      },
      "c_741": {
        "x": 192.000045776,
        "y": 198.999954224
      },
      "c_742": {
        "x": 179.000045776,
        "y": 169.499694824
      },
      "c_743": {
        "x": 222.000045776,
        "y": 142.0
      },
      "c_744": {
        "x": 201.000045776,
        "y": 46.0
      },
      "c_745": {
        "x": 154.000045776,
        "y": 46.0
      },
      "c_746": {
        "x": 114.500053406,
        "y": 119.000053406
      },
      "c_747": {
        "x": 164.400054932,
        "y": 61.9999008179
      },
      "c_748": {
        "x": 80.0000534058,
        "y": 77.9999465942
      },
      "c_749": {
        "x": 202.000045776,
        "y": 78.0
      },
      "c_75": {
        "x": 236.000045776,
        "y": 113.000022888
      },
      "c_750": {
        "x": 210.666717529,
        "y": 176.0
      },
      "c_751": {
        "x": 142.000045776,
        "y": 110.842445374
      },
      "c_752": {
        "x": 176.500045776,
        "y": 153.0
      },
      "c_753": {
        "x": 60.8889389038,
        "y": 129.0
      },
      "c_754": {
        "x": 72.0000534058,
        "y": 165.799819946
      },
      "c_755": {
        "x": 61.0000495911,
        "y": 144.500045776
      },
      "c_756": {
        "x": 66.0000534058,
        "y": 101.0
      },
      "c_757": {
        "x": 42.0000495911,
        "y": 160.000045776
      },
      "c_758": {
        "x": 78.3333816528,
        "y": 131.0
      },
      "c_759": {
        "x": 78.3333816528,
        "y": 216.500045776
      },
      "c_76": {
        "x": 59.0000495911,
        "y": 78.0
      },
      "c_760": {
        "x": 55.8889389038,
        "y": 126.0
      },
      "c_761": {
        "x": 153.526367188,
        "y": 100.84223938
      },
      "c_762": {
        "x": 100.000053406,
        "y": 209.374847412
      },
      "c_763": {
        "x": 152.60005188,
        "y": 138.0
      },
      "c_764": {
        "x": 175.60005188,
        "y": 145.0
      },
      "c_765": {
        "x": 182.500045776,
        "y": 208.0
      },
      "c_766": {
        "x": 154.000045776,
        "y": 208.833236694
      },
      "c_767": {
        "x": 189.200042725,
        "y": 118.0
      },
      "c_768": {
        "x": 99.0000534058,
        "y": 87.0000534058
      },
      "c_769": {
        "x": 255.000045776,
        "y": 159.750030518
      },
      "c_77": {
        "x": 183.500045776,
        "y": 62.0
      },
      "c_770": {
        "x": 262.000061035,
        "y": 168.0
      },
      "c_771": {
        "x": 187.000045776,
        "y": 248.500045776
      },
      "c_772": {
        "x": 150.466720581,
        "y": 219.0
      },
      "c_773": {
        "x": 89.0000534058,
        "y": 45.0
      },
      "c_774": {
        "x": 136.750045776,
        "y": 135.0
      },
      "c_775": {
        "x": 159.000045776,
        "y": 197.000045776
      },
      "c_776": {
        "x": 144.000045776,
        "y": 70.0
      },
      "c_777": {
        "x": 79.0000534058,
        "y": 97.0
      },
      "c_778": {
        "x": 45.0000495911,
        "y": 167.999893188
      },
      "c_779": {
        "x": 200.000045776,
        "y": 156.999893188
      },
      "c_78": {
        "x": 95.0000534058,
        "y": 220.0
      },
      "c_780": {
        "x": 80.0000534058,
        "y": 72.0000534058
      },
      "c_781": {
        "x": 235.000045776,
        "y": 172.666717529
      },
      "c_782": {
        "x": 226.333389282,
        "y": 181.0
      },
      "c_783": {
        "x": 87.0000534058,
        "y": 28.0
      },
      "c_784": {
        "x": 100.000053406,
        "y": 137.500045776
      },
      "c_785": {
        "x": 126.000053406,
        "y": 59.0
      },
      "c_786": {
        "x": 125.000053406,
        "y": 254.0
      },
      "c_787": {
        "x": 72.0000534058,
        "y": 111.0
      },
      "c_788": {
        "x": 204.750045776,
        "y": 182.0
      },
      "c_789": {
        "x": 119.000053406,
        "y": 235.499954224
      },
      "c_79": {
        "x": 168.000045776,
        "y": 131.0
      },
      "c_790": {
        "x": 109.000053406,
        "y": 258.0
      },
      "c_791": {
        "x": 198.000045776,
        "y": 227.0
      },
      "c_792": {
        "x": 83.5000534058,
        "y": 138.0
      },
      "c_793": {
        "x": 237.000045776,
        "y": 228.0
      },
      "c_794": {
        "x": 28.0000495911,
        "y": 150.999954224
      },
      "c_795": {
        "x": 127.000053406,
        "y": 185.500045776
      },
      "c_796": {
        "x": 182.000045776,
        "y": 153.714355469
      },
      "c_797": {
        "x": 216.000045776,
        "y": 217.0
      },
      "c_798": {
        "x": 169.000045776,
        "y": 268.000091553
      },
      "c_799": {
        "x": 138.000045776,
        "y": 64.3333358765
      },
      "c_8": {
        "x": 262.000061035,
        "y": 99.0
      },
      "c_80": {
        "x": 213.000045776,
        "y": 58.0000343323
      },
      "c_800": {
        "x": 102.000053406,
        "y": 178.000045776
      },
      "c_81": {
        "x": 90.0000534058,
        "y": 129.999954224
      },
      "c_82": {
        "x": 141.000045776,
        "y": 29.0
      },
      "c_83": {
        "x": 82.0000534058,
        "y": 83.0000534058
      },
      "c_84": {
        "x": 90.0000534058,
        "y": 258.499938965
      },
      "c_85": {
        "x": 255.000045776,
        "y": 164.75012207
      },
      "c_86": {
        "x": 152.000045776,
        "y": 251.600067139
      },
      "c_87": {
        "x": 44.0000495911,
        "y": 95.0
      },
      "c_88": {
        "x": 154.400054932,
        "y": 60.8414421082
      },
      "c_89": {
        "x": 255.000045776,
        "y": 82.0
      },
      "c_9": {
        "x": 119.500053406,
        "y": 120.999778748
      },
      "c_90": {
        "x": 118.000053406,
        "y": 55.0
      },
      "c_91": {
        "x": 167.000045776,
        "y": 250.999893188
      },
      "c_92": {
        "x": 61.0000495911,
        "y": 92.0
      },
      "c_93": {
        "x": 147.000045776,
        "y": 244.0
      },
      "c_94": {
        "x": 149.000045776,
        "y": 49.0
      },
      "c_95": {
        "x": 120.000053406,
        "y": 255.333328247
      },
      "c_96": {
        "x": 168.000045776,
        "y": 50.9999504089
      },
      "c_97": {
        "x": 105.800048828,
        "y": 187.0
      },
      "c_98": {
        "x": 61.0000495911,
        "y": 139.499954224
      },
      "c_99": {
        "x": 242.666717529,
        "y": 191.0
      },
      "var_1": {
        "x": 186.000045776,
        "y": 109.000053406
      },
      "var_10": {
        "x": 202.000045776,
        "y": 119.166519165
      },
      "var_11": {
        "x": 174.000045776,
        "y": 199.500305176
      },
      "var_12": {
        "x": 128.000045776,
        "y": 82.5714569092
      },
      "var_13": {
        "x": 211.800048828,
        "y": 158.0
      },
      "var_14": {
        "x": 124.200050354,
        "y": 177.0
      },
      "var_15": {
        "x": 108.571479797,
        "y": 151.714157104
      },
      "var_16": {
        "x": 85.0000534058,
        "y": 161.666564941
      },
      "var_17": {
        "x": 122.166717529,
        "y": 193.0
      },
      "var_18": {
        "x": 194.000045776,
        "y": 111.999946594
      },
      "var_19": {
        "x": 98.0000534058,
        "y": 95.0
      },
      "var_2": {
        "x": 81.0000534058,
        "y": 189.0
      },
      "var_20": {
        "x": 157.000045776,
        "y": 65.841545105
      },
      "var_21": {
        "x": 99.9091415405,
        "y": 103.0
      },
      "var_22": {
        "x": 91.0000534058,
        "y": 194.285720825
      },
      "var_23": {
        "x": 199.60005188,
        "y": 134.166809082
      },
      "var_24": {
        "x": 112.166717529,
        "y": 196.999954224
      },
      "var_25": {
        "x": 103.571479797,
        "y": 151.714157104
      },
      "var_26": {
        "x": 163.000045776,
        "y": 129.0
      },
      "var_27": {
        "x": 128.526367188,
        "y": 87.5715560913
      },
      "var_28": {
        "x": 171.500045776,
        "y": 153.500045776
      },
      "var_29": {
        "x": 95.8889389038,
        "y": 121.0
      },
      "var_3": {
        "x": 163.333389282,
        "y": 84.9999160767
      },
      "var_30": {
        "x": 153.333389282,
        "y": 156.999954224
      },
      "var_31": {
        "x": 216.000045776,
        "y": 164.0
      },
      "var_32": {
        "x": 115.000053406,
        "y": 106.333435059
      },
      "var_33": {
        "x": 148.000045776,
        "y": 187.000045776
      },
      "var_34": {
        "x": 88.5000534058,
        "y": 135.000045776
      },
      "var_35": {
        "x": 194.200042725,
        "y": 122.000152588
      },
      "var_36": {
        "x": 99.5000534058,
        "y": 112.0
      },
      "var_37": {
        "x": 136.000045776,
        "y": 148.0
      },
      "var_38": {
        "x": 90.8889389038,
        "y": 121.000030518
      },
      "var_39": {
        "x": 143.526367188,
        "y": 96.6001968384
      },
      "var_4": {
        "x": 162.000045776,
        "y": 163.0
      },
      "var_40": {
        "x": 198.000045776,
        "y": 151.999801636
      },
      "var_41": {
        "x": 180.000045776,
        "y": 84.9998016357
      },
      "var_42": {
        "x": 187.000045776,
        "y": 196.000106812
      },
      "var_43": {
        "x": 189.60005188,
        "y": 130.499954224
      },
      "var_44": {
        "x": 158.500045776,
        "y": 213.833328247
      },
      "var_45": {
        "x": 113.000053406,
        "y": 171.714553833
      },
      "var_46": {
        "x": 153.000045776,
        "y": 203.833129883
      },
      "var_47": {
        "x": 175.000045776,
        "y": 189.500106812
      },
      "var_48": {
        "x": 180.000045776,
        "y": 89.9999008179
      },
      "var_49": {
        "x": 177.000045776,
        "y": 163.714553833
      },
      "var_5": {
        "x": 181.000045776,
        "y": 201.0
      },
      "var_50": {
        "x": 148.000045776,
        "y": 195.0
      },
      "var_51": {
        "x": 184.000045776,
        "y": 148.714263916
      },
      "var_52": {
        "x": 110.333381653,
        "y": 161.714355469
      },
      "var_53": {
        "x": 211.000045776,
        "y": 131.333480835
      },
      "var_54": {
        "x": 148.526367188,
        "y": 100.84223938
      },
      "var_55": {
        "x": 137.500045776,
        "y": 161.0
      },
      "var_56": {
        "x": 83.0000534058,
        "y": 114.500053406
      },
      "var_57": {
        "x": 120.000053406,
        "y": 202.0
      },
      "var_58": {
        "x": 163.526367188,
        "y": 100.000213623
      },
      "var_59": {
        "x": 190.000045776,
        "y": 85.0
      },
      "var_6": {
        "x": 153.000045776,
        "y": 162.000045776
      },
      "var_60": {
        "x": 183.666717529,
        "y": 138.714050293
      },
      "var_61": {
        "x": 165.60005188,
        "y": 147.0
      },
      "var_62": {
        "x": 115.333381653,
        "y": 161.0
      },
      "var_63": {
        "x": 93.0000534058,
        "y": 99.7498474121
      },
      "var_64": {
        "x": 110.888938904,
        "y": 114.0
      },
      "var_65": {
        "x": 88.0000534058,
        "y": 115.999931335
      },
      "var_66": {
        "x": 123.526367188,
        "y": 89.0
      },
      "var_67": {
        "x": 115.800048828,
        "y": 190.0
      },
      "var_68": {
        "x": 130.500045776,
        "y": 240.600204468
      },
      "var_69": {
        "x": 174.000045776,
        "y": 184.5
      },
      "var_7": {
        "x": 91.0000534058,
        "y": 179.285415649
      },
      "var_70": {
        "x": 163.000045776,
        "y": 180.333236694
      },
      "var_8": {
        "x": 85.3333816528,
        "y": 182.0
      },
      "var_9": {
        "x": 156.500045776,
        "y": 169.0
      }
    }
  }
}
