{
  "id": "b1105bd181a19de77e9e33a63afc0607",
  "layout": {
    "bounds": [
      0.097222,
      0.097222,
      36.077,
      33.96
    ],
    "vars": {
      "c_1": {
        "x": 10.853,
        "y": 21.43
      },
      "c_10": {
        "x": 10.502,
        "y": 29.034
      },
      "c_100": {
        "x": 3.2797,
        "y": 21.483
      },
      "c_101": {
        "x": 3.4275,
        "y": 23.104
      },
      "c_102": {
        "x": 4.0722,
        "y": 24.604
      },
      "c_103": {
        "x": 21.714,
        "y": 17.314
      },
      "c_104": {
        "x": 1.5298,
        "y": 26.106
      },
      "c_105": {
        "x": 14.412,
        "y": 8.2269
      },
      "c_106": {
        "x": 22.353,
        "y": 22.331
      },
      "c_107": {
        "x": 18.362,
        "y": 11.798
      },
      "c_11": {
        "x": 11.182,
        "y": 29.704
      },
      "c_12": {
        "x": 10.728,
        "y": 29.767
      },
      "c_13": {
        "x": 9.5595,
        "y": 32.111
      },
      "c_14": {
        "x": 10.602,
        "y": 33.605
      },
      "c_15": {
        "x": 11.957,
        "y": 32.602
      },
      "c_16": {
        "x": 13.734,
        "y": 33.855
      },
      "c_17": {
        "x": 7.2218,
        "y": 27.267
      },
      "c_18": {
        "x": 3.8675,
        "y": 27.781
      },
      "c_19": {
        "x": 16.516,
        "y": 28.214
      },
      "c_2": {
        "x": 11.931,
        "y": 17.913
      },
      "c_20": {
        "x": 17.232,
        "y": 27.065
      },
      "c_21": {
        "x": 17.307,
        "y": 27.655
      },
      "c_22": {
        "x": 18.521,
        "y": 29.226
      },
      "c_23": {
        "x": 20.119,
        "y": 25.773
      },
      "c_24": {
        "x": 15.887,
        "y": 15.185
      },
      "c_25": {
        "x": 14.678,
        "y": 14.372
      },
      "c_26": {
        "x": 15.532,
        "y": 14.358
      },
      "c_27": {
        "x": 20.202,
        "y": 12.03
      },
      "c_28": {
        "x": 25.08,
        "y": 9.1958
      },
      "c_29": {
        "x": 29.725,
        "y": 8.4164
      },
      "c_3": {
        "x": 7.3401,
        "y": 17.791
      },
      "c_30": {
        "x": 32.182,
        "y": 9.0273
      },
      "c_31": {
        "x": 32.92,
        "y": 10.325
      },
      "c_32": {
        "x": 33.093,
        "y": 10.119
      },
      "c_33": {
        "x": 33.18,
        "y": 10.609
      },
      "c_34": {
        "x": 33.494,
        "y": 12.826
      },
      "c_35": {
        "x": 34.205,
        "y": 15.535
      },
      "c_36": {
        "x": 32.83,
        "y": 14.08
      },
      "c_37": {
        "x": 33.237,
        "y": 15.354
      },
      "c_38": {
        "x": 35.085,
        "y": 17.106
      },
      "c_39": {
        "x": 35.397,
        "y": 18.119
      },
      "c_4": {
        "x": 8.2766,
        "y": 19.885
      },
      "c_40": {
        "x": 35.295,
        "y": 17.872
      },
      "c_41": {
        "x": 35.663,
        "y": 20.076
      },
      "c_42": {
        "x": 35.374,
        "y": 21.812
      },
      "c_43": {
        "x": 30.508,
        "y": 13.034
      },
      "c_44": {
        "x": 27.75,
        "y": 11.238
      },
      "c_45": {
        "x": 24.968,
        "y": 10.308
      },
      "c_46": {
        "x": 21.863,
        "y": 10.026
      },
      "c_47": {
        "x": 34.293,
        "y": 13.884
      },
      "c_48": {
        "x": 34.464,
        "y": 12.183
      },
      "c_49": {
        "x": 34.534,
        "y": 13.7
      },
      "c_5": {
        "x": 12.145,
        "y": 19.92
      },
      "c_50": {
        "x": 33.971,
        "y": 18.682
      },
      "c_51": {
        "x": 33.592,
        "y": 22.727
      },
      "c_52": {
        "x": 32.305,
        "y": 22.636
      },
      "c_53": {
        "x": 32.844,
        "y": 23.124
      },
      "c_54": {
        "x": 34.457,
        "y": 25.219
      },
      "c_55": {
        "x": 34.747,
        "y": 26.136
      },
      "c_56": {
        "x": 30.995,
        "y": 24.953
      },
      "c_57": {
        "x": 29.498,
        "y": 23.534
      },
      "c_58": {
        "x": 29.499,
        "y": 24.179
      },
      "c_59": {
        "x": 30.242,
        "y": 26.695
      },
      "c_6": {
        "x": 11.379,
        "y": 25.834
      },
      "c_60": {
        "x": 29.854,
        "y": 28.055
      },
      "c_61": {
        "x": 28.802,
        "y": 28.94
      },
      "c_62": {
        "x": 25.541,
        "y": 21.752
      },
      "c_63": {
        "x": 35.357,
        "y": 13.049
      },
      "c_64": {
        "x": 35.97,
        "y": 14.312
      },
      "c_65": {
        "x": 16.434,
        "y": 11.093
      },
      "c_66": {
        "x": 15.884,
        "y": 10.081
      },
      "c_67": {
        "x": 16.298,
        "y": 10.149
      },
      "c_68": {
        "x": 18.581,
        "y": 10.451
      },
      "c_69": {
        "x": 19.98,
        "y": 12.938
      },
      "c_7": {
        "x": 10.237,
        "y": 25.017
      },
      "c_70": {
        "x": 16.541,
        "y": 6.1391
      },
      "c_71": {
        "x": 16.613,
        "y": 2.9092
      },
      "c_72": {
        "x": 15.137,
        "y": 1.0978
      },
      "c_73": {
        "x": 12.842,
        "y": 0.17859
      },
      "c_74": {
        "x": 13.475,
        "y": 0.68182
      },
      "c_75": {
        "x": 12.751,
        "y": 0.61729
      },
      "c_76": {
        "x": 10.495,
        "y": 0.097222
      },
      "c_77": {
        "x": 8.4851,
        "y": 0.53833
      },
      "c_78": {
        "x": 6.9931,
        "y": 1.4193
      },
      "c_79": {
        "x": 12.042,
        "y": 1.8416
      },
      "c_8": {
        "x": 13.709,
        "y": 25.345
      },
      "c_80": {
        "x": 11.332,
        "y": 3.4049
      },
      "c_81": {
        "x": 12.57,
        "y": 5.2165
      },
      "c_82": {
        "x": 3.028,
        "y": 16.321
      },
      "c_83": {
        "x": 4.1923,
        "y": 15.013
      },
      "c_84": {
        "x": 3.3551,
        "y": 15.348
      },
      "c_85": {
        "x": 0.68856,
        "y": 17.539
      },
      "c_86": {
        "x": 0.097222,
        "y": 20.445
      },
      "c_87": {
        "x": 0.47439,
        "y": 23.349
      },
      "c_88": {
        "x": 4.54,
        "y": 12.723
      },
      "c_89": {
        "x": 5.601,
        "y": 12.82
      },
      "c_9": {
        "x": 10.626,
        "y": 25.902
      },
      "c_90": {
        "x": 5.389,
        "y": 12.45
      },
      "c_91": {
        "x": 4.9734,
        "y": 10.832
      },
      "c_92": {
        "x": 4.0864,
        "y": 10.074
      },
      "c_93": {
        "x": 2.7019,
        "y": 10.863
      },
      "c_94": {
        "x": 8.6419,
        "y": 10.852
      },
      "c_95": {
        "x": 13.025,
        "y": 10.079
      },
      "c_96": {
        "x": 5.4983,
        "y": 20.229
      },
      "c_97": {
        "x": 6.5839,
        "y": 21.409
      },
      "c_98": {
        "x": 5.6465,
        "y": 21.043
      },
      "c_99": {
        "x": 3.8249,
        "y": 20.226
      },
      "var_1": {
        "x": 9.9896,
        "y": 19.265
      },
      "var_10": {
        "x": 11.271,
        "y": 31.133
      },
      "var_11": {
        "x": 9.9219,
        "y": 33.028
      },
      "var_12": {
        "x": 11.314,
        "y": 33.867
      },
      "var_13": {
        "x": 12.824,
        "y": 33.503
      },
      "var_14": {
        "x": 14.515,
        "y": 33.96
      },
      "var_15": {
        "x": 5.556,
        "y": 27.627
      },
      "var_16": {
        "x": 2.5333,
        "y": 27.16
      },
      "var_17": {
        "x": 17.577,
        "y": 28.675
      },
      "var_18": {
        "x": 18.572,
        "y": 26.903
      },
      "var_19": {
        "x": 18.33,
        "y": 29.592
      },
      "var_2": {
        "x": 11.619,
        "y": 23.603
      },
      "var_20": {
        "x": 21.354,
        "y": 24.219
      },
      "var_21": {
        "x": 17.578,
        "y": 13.667
      },
      "var_22": {
        "x": 15.633,
        "y": 12.159
      },
      "var_23": {
        "x": 22.672,
        "y": 10.468
      },
      "var_24": {
        "x": 27.453,
        "y": 8.4748
      },
      "var_25": {
        "x": 31.769,
        "y": 9.1604
      },
      "var_26": {
        "x": 32.731,
        "y": 9.6132
      },
      "var_27": {
        "x": 33.96,
        "y": 11.872
      },
      "var_28": {
        "x": 33.459,
        "y": 11.488
      },
      "var_29": {
        "x": 33.661,
        "y": 14.343
      },
      "var_3": {
        "x": 13.899,
        "y": 16.636
      },
      "var_30": {
        "x": 34.679,
        "y": 16.702
      },
      "var_31": {
        "x": 32.017,
        "y": 14.093
      },
      "var_32": {
        "x": 35.19,
        "y": 17.567
      },
      "var_33": {
        "x": 35.588,
        "y": 18.986
      },
      "var_34": {
        "x": 35.586,
        "y": 21.01
      },
      "var_35": {
        "x": 35.165,
        "y": 22.504
      },
      "var_36": {
        "x": 29.173,
        "y": 12.0
      },
      "var_37": {
        "x": 26.43,
        "y": 10.61
      },
      "var_38": {
        "x": 23.501,
        "y": 10.031
      },
      "var_39": {
        "x": 20.162,
        "y": 10.674
      },
      "var_4": {
        "x": 4.7838,
        "y": 16.385
      },
      "var_40": {
        "x": 34.48,
        "y": 15.86
      },
      "var_41": {
        "x": 34.833,
        "y": 12.832
      },
      "var_42": {
        "x": 33.422,
        "y": 21.386
      },
      "var_43": {
        "x": 33.801,
        "y": 23.971
      },
      "var_44": {
        "x": 31.148,
        "y": 23.728
      },
      "var_45": {
        "x": 34.322,
        "y": 26.218
      },
      "var_46": {
        "x": 35.254,
        "y": 25.741
      },
      "var_47": {
        "x": 30.303,
        "y": 25.541
      },
      "var_48": {
        "x": 27.845,
        "y": 23.111
      },
      "var_49": {
        "x": 29.845,
        "y": 27.413
      },
      "var_5": {
        "x": 6.6351,
        "y": 20.497
      },
      "var_50": {
        "x": 29.389,
        "y": 28.547
      },
      "var_51": {
        "x": 28.183,
        "y": 29.177
      },
      "var_52": {
        "x": 23.205,
        "y": 20.223
      },
      "var_53": {
        "x": 35.699,
        "y": 13.656
      },
      "var_54": {
        "x": 36.077,
        "y": 14.958
      },
      "var_55": {
        "x": 17.307,
        "y": 10.261
      },
      "var_56": {
        "x": 16.279,
        "y": 8.3366
      },
      "var_57": {
        "x": 19.448,
        "y": 11.523
      },
      "var_58": {
        "x": 20.139,
        "y": 14.37
      },
      "var_59": {
        "x": 16.713,
        "y": 4.2994
      },
      "var_6": {
        "x": 10.91,
        "y": 27.925
      },
      "var_60": {
        "x": 16.143,
        "y": 1.6948
      },
      "var_61": {
        "x": 13.906,
        "y": 0.52164
      },
      "var_62": {
        "x": 11.762,
        "y": 0.31693
      },
      "var_63": {
        "x": 12.744,
        "y": 1.1931
      },
      "var_64": {
        "x": 9.4139,
        "y": 0.22912
      },
      "var_65": {
        "x": 7.679,
        "y": 0.94462
      },
      "var_66": {
        "x": 6.458,
        "y": 1.9071
      },
      "var_67": {
        "x": 11.591,
        "y": 2.6346
      },
      "var_68": {
        "x": 11.823,
        "y": 4.2052
      },
      "var_69": {
        "x": 13.445,
        "y": 6.5521
      },
      "var_7": {
        "x": 9.048,
        "y": 26.323
      },
      "var_70": {
        "x": 1.8421,
        "y": 16.318
      },
      "var_71": {
        "x": 4.384,
        "y": 13.73
      },
      "var_72": {
        "x": 0.20926,
        "y": 18.983
      },
      "var_73": {
        "x": 0.13363,
        "y": 21.911
      },
      "var_74": {
        "x": 0.86466,
        "y": 24.794
      },
      "var_75": {
        "x": 4.9962,
        "y": 11.79
      },
      "var_76": {
        "x": 6.7278,
        "y": 11.746
      },
      "var_77": {
        "x": 4.9039,
        "y": 10.217
      },
      "var_78": {
        "x": 3.2782,
        "y": 10.328
      },
      "var_79": {
        "x": 2.3256,
        "y": 11.497
      },
      "var_8": {
        "x": 15.799,
        "y": 26.923
      },
      "var_80": {
        "x": 10.735,
        "y": 10.275
      },
      "var_81": {
        "x": 15.479,
        "y": 10.184
      },
      "var_82": {
        "x": 4.818,
        "y": 20.425
      },
      "var_83": {
        "x": 6.1526,
        "y": 21.841
      },
      "var_84": {
        "x": 3.5202,
        "y": 20.773
      },
      "var_85": {
        "x": 3.2362,
        "y": 22.303
      },
      "var_86": {
        "x": 3.6925,
        "y": 23.898
      },
      "var_87": {
        "x": 4.4304,
        "y": 25.191
      },
      "var_9": {
        "x": 9.985,
        "y": 30.656
      }
    }
  }
}
